{

	"$schema": "http://json-schema.org/draft-04/schema#",
	"description": "This is the ISO/TS 23029:2019 json schema for the message definition sese.034.002.08-SecuritiesFinancingStatusAdvice002V08.\nAll rights reserved. Generated by https://ISO20022.plus/ from eRepository on https://ISO20022.org/. Without warranty.",
	"additionalProperties": false,
	"definitions": {
				
		
		"TransactionIdentifications35": {
			"additionalProperties": false,
			"properties": {
				"AccountOwnerTransactionIdentification": {
					"$ref": "#/definitions/RestrictedFINXMax16Text",
					"type": "string"
				},
				"AccountServicerTransactionIdentification": {
					"$ref": "#/definitions/RestrictedFINXMax16Text",
					"type": "string"
				},
				"CommonIdentification": {
					"$ref": "#/definitions/RestrictedFINXMax16Text",
					"type": "string"
				}
			},
			"required": ["AccountOwnerTransactionIdentification"],
			"type": "object"
		},
		"RestrictedFINXMax16Text": {
			"description": "Specifies a character string with a maximum length of 16 characters. It has a pattern that disables the use of characters that is not part of the character set X, that is, that is not a-z A-Z / - ? : ( ) . , ‘ + , and disable the use of slash \"/\" at the beginning and end of line and double slash \"//\" within the line.",
			"minLength": 1,
			"maxLength": 16,
			"pattern": "^([0-9a-zA-Z\\-\\?:\\(\\)\\.,'\\+ ]([0-9a-zA-Z\\-\\?:\\(\\)\\.,'\\+ ]*(/[0-9a-zA-Z\\-\\?:\\(\\)\\.,'\\+ ])?)*)$",
			"type": "string"
		},
		"ProcessingStatus57Choice": {
			"oneOf":[
				{"required":["PendingCancellation"]},
				{"required":["AcknowledgedAccepted"]},
				{"required":["PendingProcessing"]},
				{"required":["Rejected"]},
				{"required":["Repair"]},
				{"required":["Cancelled"]},
				{"required":["Proprietary"]},
				{"required":["CancellationRequested"]},
				{"required":["ModificationRequested"]}
			],
			"properties":{
				"PendingCancellation": {
					"$ref": "#/definitions/PendingStatus46Choice",
					"type": "object",
					"additionalProperties": false
				},
				"AcknowledgedAccepted": {
					"$ref": "#/definitions/AcknowledgedAcceptedStatus25Choice",
					"type": "object",
					"additionalProperties": false
				},
				"PendingProcessing": {
					"$ref": "#/definitions/PendingProcessingStatus14Choice",
					"type": "object",
					"additionalProperties": false
				},
				"Rejected": {
					"$ref": "#/definitions/RejectionStatus22Choice",
					"type": "object",
					"additionalProperties": false
				},
				"Repair": {
					"$ref": "#/definitions/RepairStatus15Choice",
					"type": "object",
					"additionalProperties": false
				},
				"Cancelled": {
					"$ref": "#/definitions/CancellationStatus18Choice",
					"type": "object",
					"additionalProperties": false
				},
				"Proprietary": {
					"$ref": "#/definitions/ProprietaryStatusAndReason7",
					"type": "object",
					"additionalProperties": false
				},
				"CancellationRequested": {
					"$ref": "#/definitions/ProprietaryReason5",
					"type": "object",
					"additionalProperties": false
				},
				"ModificationRequested": {
					"$ref": "#/definitions/ProprietaryReason5",
					"type": "object",
					"additionalProperties": false
				}},
			"additionalProperties": false,
			"type": "object"
		},
		"PendingStatus46Choice": {
			"oneOf":[
				{"required":["NoSpecifiedReason"]},
				{"required":["Reason"]}
			],
			"properties":{
				"NoSpecifiedReason": {
					"$ref": "#/definitions/NoReasonCode",
					"type": "string"
				},
				"Reason": {
					"minItems":1,
					"items": {
						"$ref": "#/definitions/PendingReason20"
					},
					"type": "array"
				}},
			"additionalProperties": false,
			"type": "object"
		},
		"NoReasonCode": {
			"enum":["NORE"],			
			"type": "string"
		},
		"PendingReason20": {
			"additionalProperties": false,
			"properties": {
				"Code": {
					"$ref": "#/definitions/PendingReason37Choice",
					"type": "object",
					"additionalProperties": false
				},
				"AdditionalReasonInformation": {
					"$ref": "#/definitions/RestrictedFINXMax210Text",
					"type": "string"
				}
			},
			"required": ["Code"],
			"type": "object"
		},
		"PendingReason37Choice": {
			"oneOf":[
				{"required":["Code"]},
				{"required":["Proprietary"]}
			],
			"properties":{
				"Code": {
					"$ref": "#/definitions/PendingReason6Code",
					"type": "string"
				},
				"Proprietary": {
					"$ref": "#/definitions/GenericIdentification47",
					"type": "object",
					"additionalProperties": false
				}},
			"additionalProperties": false,
			"type": "object"
		},
		"PendingReason6Code": {
			"enum":["ADEA","OTHR","CONF","CDRE","CDCY","CDRG"],			
			"type": "string"
		},
		"GenericIdentification47": {
			"additionalProperties": false,
			"properties": {
				"Identification": {
					"$ref": "#/definitions/Exact4AlphaNumericText",
					"type": "string"
				},
				"Issuer": {
					"$ref": "#/definitions/Max4AlphaNumericText",
					"type": "string"
				},
				"SchemeName": {
					"$ref": "#/definitions/Max4AlphaNumericText",
					"type": "string"
				}
			},
			"required": ["Identification","Issuer"],
			"type": "object"
		},
		"Exact4AlphaNumericText": {
			"description": "Specifies an alphanumeric string with a length of 4 characters.",
			"pattern": "^[a-zA-Z0-9]{4}$",
			"type": "string"
		},
		"Max4AlphaNumericText": {
			"description": "Specifies an alphanumeric string with a maximum length of 4 characters.",
			"minLength": 1,
			"maxLength": 4,
			"pattern": "^[a-zA-Z0-9]{1,4}$",
			"type": "string"
		},
		"RestrictedFINXMax210Text": {
			"description": "Specifies a character string with a maximum length of 210 characters limited to character set X, that is, a-z A-Z / - ? : ( ) . , ‘ + .",
			"minLength": 1,
			"maxLength": 210,
			"pattern": "^[0-9a-zA-Z/\\-\\?:\\(\\)\\.\\n\\r,'\\+ ]{1,210}$",
			"type": "string"
		},
		"AcknowledgedAcceptedStatus25Choice": {
			"oneOf":[
				{"required":["NoSpecifiedReason"]},
				{"required":["Reason"]}
			],
			"properties":{
				"NoSpecifiedReason": {
					"$ref": "#/definitions/NoReasonCode",
					"type": "string"
				},
				"Reason": {
					"minItems":1,
					"items": {
						"$ref": "#/definitions/AcknowledgementReason13"
					},
					"type": "array"
				}},
			"additionalProperties": false,
			"type": "object"
		},
		"AcknowledgementReason13": {
			"additionalProperties": false,
			"properties": {
				"Code": {
					"$ref": "#/definitions/AcknowledgementReason16Choice",
					"type": "object",
					"additionalProperties": false
				},
				"AdditionalReasonInformation": {
					"$ref": "#/definitions/RestrictedFINXMax210Text",
					"type": "string"
				}
			},
			"required": ["Code"],
			"type": "object"
		},
		"AcknowledgementReason16Choice": {
			"oneOf":[
				{"required":["Code"]},
				{"required":["Proprietary"]}
			],
			"properties":{
				"Code": {
					"$ref": "#/definitions/AcknowledgementReason5Code",
					"type": "string"
				},
				"Proprietary": {
					"$ref": "#/definitions/GenericIdentification47",
					"type": "object",
					"additionalProperties": false
				}},
			"additionalProperties": false,
			"type": "object"
		},
		"AcknowledgementReason5Code": {
			"enum":["ADEA","SMPG","LATE","NSTP","RQWV","OTHR","CDCY","CDRG","CDRE"],			
			"type": "string"
		},
		"PendingProcessingStatus14Choice": {
			"oneOf":[
				{"required":["NoSpecifiedReason"]},
				{"required":["Reason"]}
			],
			"properties":{
				"NoSpecifiedReason": {
					"$ref": "#/definitions/NoReasonCode",
					"type": "string"
				},
				"Reason": {
					"minItems":1,
					"items": {
						"$ref": "#/definitions/PendingProcessingReason11"
					},
					"type": "array"
				}},
			"additionalProperties": false,
			"type": "object"
		},
		"PendingProcessingReason11": {
			"additionalProperties": false,
			"properties": {
				"Code": {
					"$ref": "#/definitions/PendingProcessingReason13Choice",
					"type": "object",
					"additionalProperties": false
				},
				"AdditionalReasonInformation": {
					"$ref": "#/definitions/RestrictedFINXMax210Text",
					"type": "string"
				}
			},
			"required": ["Code"],
			"type": "object"
		},
		"PendingProcessingReason13Choice": {
			"oneOf":[
				{"required":["Code"]},
				{"required":["Proprietary"]}
			],
			"properties":{
				"Code": {
					"$ref": "#/definitions/PendingProcessingReason1Code",
					"type": "string"
				},
				"Proprietary": {
					"$ref": "#/definitions/GenericIdentification47",
					"type": "object",
					"additionalProperties": false
				}},
			"additionalProperties": false,
			"type": "object"
		},
		"PendingProcessingReason1Code": {
			"enum":["ADEA","CAIS","DOCY","BLOC","MUNO","GLOB","YCOL","COLL","FLIM","NOFX","LACK","LALO","MONY","MINO","OTHR","DENO","LIQU","CERT","NEXT"],			
			"type": "string"
		},
		"RejectionStatus22Choice": {
			"oneOf":[
				{"required":["NoSpecifiedReason"]},
				{"required":["Reason"]}
			],
			"properties":{
				"NoSpecifiedReason": {
					"$ref": "#/definitions/NoReasonCode",
					"type": "string"
				},
				"Reason": {
					"minItems":1,
					"items": {
						"$ref": "#/definitions/RejectionReason34"
					},
					"type": "array"
				}},
			"additionalProperties": false,
			"type": "object"
		},
		"RejectionReason34": {
			"additionalProperties": false,
			"properties": {
				"Code": {
					"$ref": "#/definitions/RejectionReason28Choice",
					"type": "object",
					"additionalProperties": false
				},
				"AdditionalReasonInformation": {
					"$ref": "#/definitions/RestrictedFINXMax210Text",
					"type": "string"
				}
			},
			"required": ["Code"],
			"type": "object"
		},
		"RejectionReason28Choice": {
			"oneOf":[
				{"required":["Code"]},
				{"required":["Proprietary"]}
			],
			"properties":{
				"Code": {
					"$ref": "#/definitions/RejectionReason38Code",
					"type": "string"
				},
				"Proprietary": {
					"$ref": "#/definitions/GenericIdentification47",
					"type": "object",
					"additionalProperties": false
				}},
			"additionalProperties": false,
			"type": "object"
		},
		"RejectionReason38Code": {
			"enum":["SAFE","DQUA","ADEA","DSEC","LATE","CADE","CASH","DDEA","FORF","REPA","REPO","REPP","RERT","RSPR","DTRD","PLCE","RTGS","NCRR","PHYS","REFE","DMON","MINO","BATC","MUNO","TXST","SETS","IIND","CAEV","CASY","DDAT","SETR","TERM","VASU","SDUT","INPS","OTHR","IEXE","ICUS","ICAG","DEPT","PLIS","INVE"],			
			"type": "string"
		},
		"RepairStatus15Choice": {
			"oneOf":[
				{"required":["NoSpecifiedReason"]},
				{"required":["Reason"]}
			],
			"properties":{
				"NoSpecifiedReason": {
					"$ref": "#/definitions/NoReasonCode",
					"type": "string"
				},
				"Reason": {
					"minItems":1,
					"items": {
						"$ref": "#/definitions/RepairReason11"
					},
					"type": "array"
				}},
			"additionalProperties": false,
			"type": "object"
		},
		"RepairReason11": {
			"additionalProperties": false,
			"properties": {
				"Code": {
					"$ref": "#/definitions/RepairReason13Choice",
					"type": "object",
					"additionalProperties": false
				},
				"AdditionalReasonInformation": {
					"$ref": "#/definitions/RestrictedFINXMax210Text",
					"type": "string"
				}
			},
			"required": ["Code"],
			"type": "object"
		},
		"RepairReason13Choice": {
			"oneOf":[
				{"required":["Code"]},
				{"required":["Proprietary"]}
			],
			"properties":{
				"Code": {
					"$ref": "#/definitions/RepairReason5Code",
					"type": "string"
				},
				"Proprietary": {
					"$ref": "#/definitions/GenericIdentification47",
					"type": "object",
					"additionalProperties": false
				}},
			"additionalProperties": false,
			"type": "object"
		},
		"RepairReason5Code": {
			"enum":["BATC","CADE","CAEV","CASH","CASY","DDAT","DDEA","DMON","DQUA","DSEC","DTRD","FORF","IIND","MINO","MUNO","NCRR","PHYS","PLCE","REFE","REPA","REPO","REPP","RERT","RSPR","RTGS","SAFE","SETR","SETS","TERM","TXST","VASU","INPS","SDUT","OTHR","DEPT","IEXE","ICUS","ICAG"],			
			"type": "string"
		},
		"CancellationStatus18Choice": {
			"oneOf":[
				{"required":["NoSpecifiedReason"]},
				{"required":["Reason"]}
			],
			"properties":{
				"NoSpecifiedReason": {
					"$ref": "#/definitions/NoReasonCode",
					"type": "string"
				},
				"Reason": {
					"minItems":1,
					"items": {
						"$ref": "#/definitions/CancellationReason15"
					},
					"type": "array"
				}},
			"additionalProperties": false,
			"type": "object"
		},
		"CancellationReason15": {
			"additionalProperties": false,
			"properties": {
				"Code": {
					"$ref": "#/definitions/CancellationReason25Choice",
					"type": "object",
					"additionalProperties": false
				},
				"AdditionalReasonInformation": {
					"$ref": "#/definitions/RestrictedFINXMax210Text",
					"type": "string"
				}
			},
			"required": ["Code"],
			"type": "object"
		},
		"CancellationReason25Choice": {
			"oneOf":[
				{"required":["Code"]},
				{"required":["Proprietary"]}
			],
			"properties":{
				"Code": {
					"$ref": "#/definitions/CancelledStatusReason9Code",
					"type": "string"
				},
				"Proprietary": {
					"$ref": "#/definitions/GenericIdentification47",
					"type": "object",
					"additionalProperties": false
				}},
			"additionalProperties": false,
			"type": "object"
		},
		"CancelledStatusReason9Code": {
			"enum":["CANI","CANS","CSUB","CXLR","CANT","CANZ","CORP","SCEX","OTHR"],			
			"type": "string"
		},
		"ProprietaryStatusAndReason7": {
			"additionalProperties": false,
			"properties": {
				"ProprietaryStatus": {
					"$ref": "#/definitions/GenericIdentification47",
					"type": "object",
					"additionalProperties": false
				},
				"ProprietaryReason": {
					"items": {
						"$ref": "#/definitions/ProprietaryReason5"
					},
					"type": "array"
				}
			},
			"required": ["ProprietaryStatus"],
			"type": "object"
		},
		"ProprietaryReason5": {
			"additionalProperties": false,
			"properties": {
				"Reason": {
					"$ref": "#/definitions/GenericIdentification47",
					"type": "object",
					"additionalProperties": false
				},
				"AdditionalReasonInformation": {
					"$ref": "#/definitions/RestrictedFINXMax210Text",
					"type": "string"
				}
			},
			"type": "object"
		},
		"MatchingStatus29Choice": {
			"oneOf":[
				{"required":["Matched"]},
				{"required":["Unmatched"]},
				{"required":["Proprietary"]}
			],
			"properties":{
				"Matched": {
					"$ref": "#/definitions/ProprietaryReason5",
					"type": "object",
					"additionalProperties": false
				},
				"Unmatched": {
					"$ref": "#/definitions/UnmatchedStatus19Choice",
					"type": "object",
					"additionalProperties": false
				},
				"Proprietary": {
					"$ref": "#/definitions/ProprietaryStatusAndReason7",
					"type": "object",
					"additionalProperties": false
				}},
			"additionalProperties": false,
			"type": "object"
		},
		"UnmatchedStatus19Choice": {
			"oneOf":[
				{"required":["NoSpecifiedReason"]},
				{"required":["Reason"]}
			],
			"properties":{
				"NoSpecifiedReason": {
					"$ref": "#/definitions/NoReasonCode",
					"type": "string"
				},
				"Reason": {
					"minItems":1,
					"items": {
						"$ref": "#/definitions/UnmatchedReason18"
					},
					"type": "array"
				}},
			"additionalProperties": false,
			"type": "object"
		},
		"UnmatchedReason18": {
			"additionalProperties": false,
			"properties": {
				"Code": {
					"$ref": "#/definitions/UnmatchedReason25Choice",
					"type": "object",
					"additionalProperties": false
				},
				"AdditionalReasonInformation": {
					"$ref": "#/definitions/RestrictedFINXMax210Text",
					"type": "string"
				}
			},
			"required": ["Code"],
			"type": "object"
		},
		"UnmatchedReason25Choice": {
			"oneOf":[
				{"required":["Code"]},
				{"required":["Proprietary"]}
			],
			"properties":{
				"Code": {
					"$ref": "#/definitions/UnmatchedReason13Code",
					"type": "string"
				},
				"Proprietary": {
					"$ref": "#/definitions/GenericIdentification47",
					"type": "object",
					"additionalProperties": false
				}},
			"additionalProperties": false,
			"type": "object"
		},
		"UnmatchedReason13Code": {
			"enum":["ACRU","CMIS","DDAT","DELN","DEPT","DMON","DDEA","DQUA","CADE","ADEA","SETR","SETS","DSEC","VASU","DTRA","REPO","CLAT","RERT","REPA","REPP","PHYS","IIND","FRAP","PLCE","PODU","FORF","REGD","RTGS","ICAG","CPCA","IEXE","NCRR","LEOG","NMAS","SAFE","DTRD","LATE","TERM","TXST","ICUS","OTHR","INPS","INVE","PLIS","DCMX","DMCT"],			
			"type": "string"
		},
		"SettlementStatus21Choice": {
			"oneOf":[
				{"required":["Pending"]},
				{"required":["Failing"]},
				{"required":["Proprietary"]}
			],
			"properties":{
				"Pending": {
					"$ref": "#/definitions/PendingStatus47Choice",
					"type": "object",
					"additionalProperties": false
				},
				"Failing": {
					"$ref": "#/definitions/FailingStatus12Choice",
					"type": "object",
					"additionalProperties": false
				},
				"Proprietary": {
					"$ref": "#/definitions/ProprietaryStatusAndReason7",
					"type": "object",
					"additionalProperties": false
				}},
			"additionalProperties": false,
			"type": "object"
		},
		"PendingStatus47Choice": {
			"oneOf":[
				{"required":["NoSpecifiedReason"]},
				{"required":["Reason"]}
			],
			"properties":{
				"NoSpecifiedReason": {
					"$ref": "#/definitions/NoReasonCode",
					"type": "string"
				},
				"Reason": {
					"minItems":1,
					"items": {
						"$ref": "#/definitions/PendingReason21"
					},
					"type": "array"
				}},
			"additionalProperties": false,
			"type": "object"
		},
		"PendingReason21": {
			"additionalProperties": false,
			"properties": {
				"Code": {
					"$ref": "#/definitions/PendingReason38Choice",
					"type": "object",
					"additionalProperties": false
				},
				"AdditionalReasonInformation": {
					"$ref": "#/definitions/RestrictedFINXMax210Text",
					"type": "string"
				}
			},
			"required": ["Code"],
			"type": "object"
		},
		"PendingReason38Choice": {
			"oneOf":[
				{"required":["Code"]},
				{"required":["Proprietary"]}
			],
			"properties":{
				"Code": {
					"$ref": "#/definitions/PendingReason1Code",
					"type": "string"
				},
				"Proprietary": {
					"$ref": "#/definitions/GenericIdentification47",
					"type": "object",
					"additionalProperties": false
				}},
			"additionalProperties": false,
			"type": "object"
		},
		"PendingReason1Code": {
			"enum":["AWMO","ADEA","CAIS","REFU","AWSH","PHSE","TAMM","DOCY","DOCC","BLOC","CHAS","NEWI","CLAC","MUNO","GLOB","PREA","PART","NMAS","CMON","YCOL","COLL","DEPO","FLIM","NOFX","INCA","LINK","FUTU","LACK","LALO","MONY","NCON","REFS","SDUT","BATC","CYCL","SBLO","CPEC","MINO","IAAD","OTHR","PHCK","BENO","BOTH","CLHT","DENO","DISA","DKNY","FROZ","LAAW","LATE","LIQU","PRCY","REGT","SETS","CERT","PRSY"],			
			"type": "string"
		},
		"FailingStatus12Choice": {
			"oneOf":[
				{"required":["NoSpecifiedReason"]},
				{"required":["Reason"]}
			],
			"properties":{
				"NoSpecifiedReason": {
					"$ref": "#/definitions/NoReasonCode",
					"type": "string"
				},
				"Reason": {
					"minItems":1,
					"items": {
						"$ref": "#/definitions/FailingReason10"
					},
					"type": "array"
				}},
			"additionalProperties": false,
			"type": "object"
		},
		"FailingReason10": {
			"additionalProperties": false,
			"properties": {
				"Code": {
					"$ref": "#/definitions/FailingReason11Choice",
					"type": "object",
					"additionalProperties": false
				},
				"AdditionalReasonInformation": {
					"$ref": "#/definitions/RestrictedFINXMax210Text",
					"type": "string"
				}
			},
			"required": ["Code"],
			"type": "object"
		},
		"FailingReason11Choice": {
			"oneOf":[
				{"required":["Code"]},
				{"required":["Proprietary"]}
			],
			"properties":{
				"Code": {
					"$ref": "#/definitions/FailingReason2Code",
					"type": "string"
				},
				"Proprietary": {
					"$ref": "#/definitions/GenericIdentification47",
					"type": "object",
					"additionalProperties": false
				}},
			"additionalProperties": false,
			"type": "object"
		},
		"FailingReason2Code": {
			"enum":["AWMO","ADEA","CAIS","AWSH","PHSE","DOCY","DOCC","BLOC","CHAS","NEWI","CLAC","MUNO","GLOB","PREA","PART","CMON","YCOL","COLL","DEPO","FLIM","NOFX","INCA","LINK","LACK","LALO","MONY","NCON","REFS","SDUT","BATC","CYCL","SBLO","CPEC","MINO","IAAD","OTHR","PHCK","BENO","BOTH","CLHT","DENO","DISA","DKNY","FROZ","LAAW","LATE","LIQU","PRCY","REGT","SETS","BYIY","CANR","CERT","OBJT","STCD","CLAT","MLAT","PRSY","CSDH","CVAL","CDLR","INBC"],			
			"type": "string"
		},
		"RepoCallRequestStatus9Choice": {
			"oneOf":[
				{"required":["AcknowledgedAccepted"]},
				{"required":["Denied"]},
				{"required":["Proprietary"]}
			],
			"properties":{
				"AcknowledgedAccepted": {
					"$ref": "#/definitions/AcknowledgedAcceptedStatus27Choice",
					"type": "object",
					"additionalProperties": false
				},
				"Denied": {
					"$ref": "#/definitions/DeniedStatus18Choice",
					"type": "object",
					"additionalProperties": false
				},
				"Proprietary": {
					"$ref": "#/definitions/ProprietaryStatusAndReason7",
					"type": "object",
					"additionalProperties": false
				}},
			"additionalProperties": false,
			"type": "object"
		},
		"AcknowledgedAcceptedStatus27Choice": {
			"oneOf":[
				{"required":["NoSpecifiedReason"]},
				{"required":["Reason"]}
			],
			"properties":{
				"NoSpecifiedReason": {
					"$ref": "#/definitions/NoReasonCode",
					"type": "string"
				},
				"Reason": {
					"minItems":1,
					"items": {
						"$ref": "#/definitions/AcknowledgementReason15"
					},
					"type": "array"
				}},
			"additionalProperties": false,
			"type": "object"
		},
		"AcknowledgementReason15": {
			"additionalProperties": false,
			"properties": {
				"Code": {
					"$ref": "#/definitions/AcknowledgementReason18Choice",
					"type": "object",
					"additionalProperties": false
				},
				"AdditionalReasonInformation": {
					"$ref": "#/definitions/RestrictedFINXMax210Text",
					"type": "string"
				}
			},
			"required": ["Code"],
			"type": "object"
		},
		"AcknowledgementReason18Choice": {
			"oneOf":[
				{"required":["Code"]},
				{"required":["Proprietary"]}
			],
			"properties":{
				"Code": {
					"$ref": "#/definitions/RepoCallAcknowledgementReason2Code",
					"type": "string"
				},
				"Proprietary": {
					"$ref": "#/definitions/GenericIdentification47",
					"type": "object",
					"additionalProperties": false
				}},
			"additionalProperties": false,
			"type": "object"
		},
		"RepoCallAcknowledgementReason2Code": {
			"enum":["ADEA","CALD","CALP"],			
			"type": "string"
		},
		"DeniedStatus18Choice": {
			"oneOf":[
				{"required":["NoSpecifiedReason"]},
				{"required":["Reason"]}
			],
			"properties":{
				"NoSpecifiedReason": {
					"$ref": "#/definitions/NoReasonCode",
					"type": "string"
				},
				"Reason": {
					"minItems":1,
					"items": {
						"$ref": "#/definitions/DeniedReason13"
					},
					"type": "array"
				}},
			"additionalProperties": false,
			"type": "object"
		},
		"DeniedReason13": {
			"additionalProperties": false,
			"properties": {
				"Code": {
					"$ref": "#/definitions/DeniedReason18Choice",
					"type": "object",
					"additionalProperties": false
				},
				"AdditionalReasonInformation": {
					"$ref": "#/definitions/RestrictedFINXMax210Text",
					"type": "string"
				}
			},
			"required": ["Code"],
			"type": "object"
		},
		"DeniedReason18Choice": {
			"oneOf":[
				{"required":["Code"]},
				{"required":["Proprietary"]}
			],
			"properties":{
				"Code": {
					"$ref": "#/definitions/DeniedReason3Code",
					"type": "string"
				},
				"Proprietary": {
					"$ref": "#/definitions/GenericIdentification47",
					"type": "object",
					"additionalProperties": false
				}},
			"additionalProperties": false,
			"type": "object"
		},
		"DeniedReason3Code": {
			"enum":["ADEA","DCAL","DFOR","LATE","OTHR"],			
			"type": "string"
		},
		"SecuritiesFinancingTransactionDetails49": {
			"additionalProperties": false,
			"properties": {
				"SecuritiesFinancingTradeIdentification": {
					"$ref": "#/definitions/RestrictedFINXMax52Text",
					"type": "string"
				},
				"ClosingLegIdentification": {
					"$ref": "#/definitions/RestrictedFINXMax16Text",
					"type": "string"
				},
				"PoolIdentification": {
					"$ref": "#/definitions/RestrictedFINXMax16Text",
					"type": "string"
				},
				"CorporateActionEventIdentification": {
					"$ref": "#/definitions/RestrictedFINXMax16Text",
					"type": "string"
				},
				"TripartyAgentServiceProviderCollateralTransactionIdentification": {
					"$ref": "#/definitions/RestrictedFINXMax16Text",
					"type": "string"
				},
				"ClientTripartyCollateralTransactionIdentification": {
					"$ref": "#/definitions/RestrictedFINXMax16Text",
					"type": "string"
				},
				"AccountOwner": {
					"$ref": "#/definitions/PartyIdentification156",
					"type": "object",
					"additionalProperties": false
				},
				"SafekeepingAccount": {
					"$ref": "#/definitions/SecuritiesAccount30",
					"type": "object",
					"additionalProperties": false
				},
				"SafekeepingPlace": {
					"$ref": "#/definitions/SafeKeepingPlace4",
					"type": "object",
					"additionalProperties": false
				},
				"PlaceOfTrade": {
					"$ref": "#/definitions/PlaceOfTradeIdentification2",
					"type": "object",
					"additionalProperties": false
				},
				"FinancialInstrumentIdentification": {
					"$ref": "#/definitions/SecurityIdentification20",
					"type": "object",
					"additionalProperties": false
				},
				"SettlementQuantity": {
					"$ref": "#/definitions/Quantity10Choice",
					"type": "object",
					"additionalProperties": false
				},
				"OpeningSettlementAmount": {
					"$ref": "#/definitions/AmountAndDirection67",
					"type": "object",
					"additionalProperties": false
				},
				"TerminationTransactionAmount": {
					"$ref": "#/definitions/AmountAndDirection59",
					"type": "object",
					"additionalProperties": false
				},
				"OpeningSettlementDate": {
					"$ref": "#/definitions/SettlementDate32Choice",
					"type": "object",
					"additionalProperties": false
				},
				"TerminationDate": {
					"$ref": "#/definitions/TerminationDate7Choice",
					"type": "object",
					"additionalProperties": false
				},
				"TradeDate": {
					"$ref": "#/definitions/TradeDate9Choice",
					"type": "object",
					"additionalProperties": false
				},
				"ExpectedSettlementDate": {
					"$ref": "#/definitions/DateAndDateTime2Choice",
					"type": "object",
					"additionalProperties": false
				},
				"ExpectedValueDate": {
					"$ref": "#/definitions/DateAndDateTime2Choice",
					"type": "object",
					"additionalProperties": false
				},
				"LateDeliveryDate": {
					"$ref": "#/definitions/DateAndDateTime2Choice",
					"type": "object",
					"additionalProperties": false
				},
				"RateChangeDate": {
					"$ref": "#/definitions/DateAndDateTime2Choice",
					"type": "object",
					"additionalProperties": false
				},
				"SecuritiesFinancingTransactionType": {
					"$ref": "#/definitions/SecuritiesFinancingTransactionType2Code",
					"type": "string"
				},
				"SecuritiesMovementType": {
					"$ref": "#/definitions/ReceiveDelivery1Code",
					"type": "string"
				},
				"Payment": {
					"$ref": "#/definitions/DeliveryReceiptType2Code",
					"type": "string"
				},
				"SettlementParameters": {
					"$ref": "#/definitions/SettlementDetails173",
					"type": "object",
					"additionalProperties": false
				},
				"RateType": {
					"$ref": "#/definitions/RateType67Choice",
					"type": "object",
					"additionalProperties": false
				},
				"VariableRateSupport": {
					"$ref": "#/definitions/RateName2",
					"type": "object",
					"additionalProperties": false
				},
				"RepurchaseRate": {
					"$ref": "#/definitions/Rate2",
					"type": "object",
					"additionalProperties": false
				},
				"StockLoanMargin": {
					"$ref": "#/definitions/Rate2",
					"type": "object",
					"additionalProperties": false
				},
				"SecuritiesHaircut": {
					"$ref": "#/definitions/Rate2",
					"type": "object",
					"additionalProperties": false
				},
				"PricingRate": {
					"$ref": "#/definitions/RateOrName2Choice",
					"type": "object",
					"additionalProperties": false
				},
				"Spread": {
					"$ref": "#/definitions/Rate2",
					"type": "object",
					"additionalProperties": false
				},
				"DeliveringSettlementParties": {
					"$ref": "#/definitions/SettlementParties83",
					"type": "object",
					"additionalProperties": false
				},
				"ReceivingSettlementParties": {
					"$ref": "#/definitions/SettlementParties83",
					"type": "object",
					"additionalProperties": false
				},
				"Investor": {
					"$ref": "#/definitions/PartyIdentification170",
					"type": "object",
					"additionalProperties": false
				},
				"SettlementInstructionProcessingAdditionalDetails": {
					"$ref": "#/definitions/RestrictedFINXMax350Text",
					"type": "string"
				}
			},
			"required": ["SafekeepingAccount","FinancialInstrumentIdentification","SettlementQuantity","OpeningSettlementDate","SecuritiesFinancingTransactionType","SecuritiesMovementType","Payment"],
			"type": "object"
		},
		"RestrictedFINXMax52Text": {
			"description": "Specifies a character string with a maximum length of 52 characters limited to character set X, that is, a-z A-Z / - ? : ( ) . , ‘ + .",
			"minLength": 1,
			"maxLength": 52,
			"pattern": "^[0-9a-zA-Z/\\-\\?:\\(\\)\\.,'\\+ ]{1,52}$",
			"type": "string"
		},
		"PartyIdentification156": {
			"additionalProperties": false,
			"properties": {
				"Identification": {
					"$ref": "#/definitions/PartyIdentification136Choice",
					"type": "object",
					"additionalProperties": false
				},
				"LEI": {
					"$ref": "#/definitions/LEIIdentifier",
					"type": "string"
				}
			},
			"required": ["Identification"],
			"type": "object"
		},
		"PartyIdentification136Choice": {
			"oneOf":[
				{"required":["AnyBIC"]},
				{"required":["ProprietaryIdentification"]}
			],
			"properties":{
				"AnyBIC": {
					"$ref": "#/definitions/AnyBICDec2014Identifier",
					"type": "string"
				},
				"ProprietaryIdentification": {
					"$ref": "#/definitions/GenericIdentification84",
					"type": "object",
					"additionalProperties": false
				}},
			"additionalProperties": false,
			"type": "object"
		},
		"AnyBICDec2014Identifier" : {
		
			"pattern":"^[A-Z0-9]{4,4}[A-Z]{2,2}[A-Z0-9]{2,2}([A-Z0-9]{3,3}){0,1}$",
			"type":"string"
		},
		"GenericIdentification84": {
			"additionalProperties": false,
			"properties": {
				"Identification": {
					"$ref": "#/definitions/RestrictedFINXMax34Text",
					"type": "string"
				},
				"Issuer": {
					"$ref": "#/definitions/Max4AlphaNumericText",
					"type": "string"
				},
				"SchemeName": {
					"$ref": "#/definitions/Max4AlphaNumericText",
					"type": "string"
				}
			},
			"required": ["Identification","Issuer"],
			"type": "object"
		},
		"RestrictedFINXMax34Text": {
			"description": "Specifies a character string with a maximum length of 34 characters. It has a pattern that disables the use of characters that is not part of the character set X, that is, that is not a-z A-Z / - ? : ( ) . , ‘ + , and disable the use of slash \"/\" at the beginning and end of line and double slash \"//\" within the line.",
			"minLength": 1,
			"maxLength": 34,
			"pattern": "^([0-9a-zA-Z\\-\\?:\\(\\)\\.,'\\+ ]([0-9a-zA-Z\\-\\?:\\(\\)\\.,'\\+ ]*(/[0-9a-zA-Z\\-\\?:\\(\\)\\.,'\\+ ])?)*)$",
			"type": "string"
		},
		"LEIIdentifier" : {
		
			"pattern":"^[A-Z0-9]{18,18}[0-9]{2,2}$",
			"type":"string"
		},
		"SecuritiesAccount30": {
			"additionalProperties": false,
			"properties": {
				"Identification": {
					"$ref": "#/definitions/RestrictedFINXMax35Text",
					"type": "string"
				},
				"Type": {
					"$ref": "#/definitions/GenericIdentification47",
					"type": "object",
					"additionalProperties": false
				},
				"Name": {
					"$ref": "#/definitions/Max70Text",
					"type": "string"
				}
			},
			"required": ["Identification"],
			"type": "object"
		},
		"RestrictedFINXMax35Text": {
			"description": "Specifies a character string with a maximum length of 35 characters limited to character set X, that is, a-z A-Z / - ? : ( ) . , ‘ + .",
			"minLength": 1,
			"maxLength": 35,
			"pattern": "^[0-9a-zA-Z/\\-\\?:\\(\\)\\.,'\\+ ]{1,35}$",
			"type": "string"
		},
		"Max70Text": {
			"description": "Specifies a character string with a maximum length of 70characters.",
			"minLength": 1,
			"maxLength": 70,
			"type": "string"
		},
		"SafeKeepingPlace4": {
			"additionalProperties": false,
			"properties": {
				"SafekeepingPlaceFormat": {
					"$ref": "#/definitions/SafekeepingPlaceFormat39Choice",
					"type": "object",
					"additionalProperties": false
				},
				"LEI": {
					"$ref": "#/definitions/LEIIdentifier",
					"type": "string"
				}
			},
			"type": "object"
		},
		"SafekeepingPlaceFormat39Choice": {
			"oneOf":[
				{"required":["Identification"]},
				{"required":["Country"]},
				{"required":["TypeAndIdentification"]},
				{"required":["Proprietary"]}
			],
			"properties":{
				"Identification": {
					"$ref": "#/definitions/SafekeepingPlaceTypeAndText15",
					"type": "object",
					"additionalProperties": false
				},
				"Country": {
					"$ref": "#/definitions/CountryCode",
					"type": "string"
				},
				"TypeAndIdentification": {
					"$ref": "#/definitions/SafekeepingPlaceTypeAndIdentification1",
					"type": "object",
					"additionalProperties": false
				},
				"Proprietary": {
					"$ref": "#/definitions/GenericIdentification85",
					"type": "object",
					"additionalProperties": false
				}},
			"additionalProperties": false,
			"type": "object"
		},
		"SafekeepingPlaceTypeAndText15": {
			"additionalProperties": false,
			"properties": {
				"SafekeepingPlaceType": {
					"$ref": "#/definitions/SafekeepingPlace3Code",
					"type": "string"
				},
				"Identification": {
					"$ref": "#/definitions/RestrictedFINXMax30Text",
					"type": "string"
				}
			},
			"required": ["SafekeepingPlaceType"],
			"type": "object"
		},
		"SafekeepingPlace3Code": {
			"enum":["SHHE"],			
			"type": "string"
		},
		"RestrictedFINXMax30Text": {
			"description": "Specifies a character string with a maximum length of 30 characters. It has a pattern that disables the use of characters that is not part of the character set X, that is, that is not a-z A-Z / - ? : ( ) . , ‘ + , and disable the use of slash \"/\" at the beginning and end of line and double slash \"//\" within the line.",
			"minLength": 1,
			"maxLength": 30,
			"pattern": "^([0-9a-zA-Z\\-\\?:\\(\\)\\.,'\\+ ]([0-9a-zA-Z\\-\\?:\\(\\)\\.,'\\+ ]*(/[0-9a-zA-Z\\-\\?:\\(\\)\\.,'\\+ ])?)*)$",
			"type": "string"
		},
		"CountryCode": {
			"pattern": "^[A-Z]{2,2}$",			
			"type": "string"
		},
		"SafekeepingPlaceTypeAndIdentification1": {
			"additionalProperties": false,
			"properties": {
				"SafekeepingPlaceType": {
					"$ref": "#/definitions/SafekeepingPlace1Code",
					"type": "string"
				},
				"Identification": {
					"$ref": "#/definitions/AnyBICDec2014Identifier",
					"type": "string"
				}
			},
			"required": ["SafekeepingPlaceType","Identification"],
			"type": "object"
		},
		"SafekeepingPlace1Code": {
			"enum":["CUST","ICSD","NCSD","SHHE"],			
			"type": "string"
		},
		"GenericIdentification85": {
			"additionalProperties": false,
			"properties": {
				"Type": {
					"$ref": "#/definitions/GenericIdentification47",
					"type": "object",
					"additionalProperties": false
				},
				"Identification": {
					"$ref": "#/definitions/RestrictedFINXMax30Text",
					"type": "string"
				}
			},
			"required": ["Type"],
			"type": "object"
		},
		"PlaceOfTradeIdentification2": {
			"additionalProperties": false,
			"properties": {
				"MarketTypeAndIdentification": {
					"$ref": "#/definitions/MarketIdentification90",
					"type": "object",
					"additionalProperties": false
				},
				"LEI": {
					"$ref": "#/definitions/LEIIdentifier",
					"type": "string"
				}
			},
			"type": "object"
		},
		"MarketIdentification90": {
			"additionalProperties": false,
			"properties": {
				"Identification": {
					"$ref": "#/definitions/MarketIdentification2Choice",
					"type": "object",
					"additionalProperties": false
				},
				"Type": {
					"$ref": "#/definitions/MarketType16Choice",
					"type": "object",
					"additionalProperties": false
				}
			},
			"required": ["Type"],
			"type": "object"
		},
		"MarketIdentification2Choice": {
			"oneOf":[
				{"required":["MarketIdentifierCode"]},
				{"required":["Description"]}
			],
			"properties":{
				"MarketIdentifierCode": {
					"$ref": "#/definitions/MICIdentifier",
					"type": "string"
				},
				"Description": {
					"$ref": "#/definitions/RestrictedFINXMax30Text",
					"type": "string"
				}},
			"additionalProperties": false,
			"type": "object"
		},
		"MICIdentifier" : {
		
			"pattern":"^[A-Z0-9]{4,4}$",
			"type":"string"
		},
		"MarketType16Choice": {
			"oneOf":[
				{"required":["Code"]},
				{"required":["Proprietary"]}
			],
			"properties":{
				"Code": {
					"$ref": "#/definitions/MarketType2Code",
					"type": "string"
				},
				"Proprietary": {
					"$ref": "#/definitions/GenericIdentification47",
					"type": "object",
					"additionalProperties": false
				}},
			"additionalProperties": false,
			"type": "object"
		},
		"MarketType2Code": {
			"enum":["PRIM","SECM","OTCO","VARI","EXCH"],			
			"type": "string"
		},
		"SecurityIdentification20": {
			"additionalProperties": false,
			"properties": {
				"ISIN": {
					"$ref": "#/definitions/ISINOct2015Identifier",
					"type": "string"
				},
				"OtherIdentification": {
					"items": {
						"$ref": "#/definitions/OtherIdentification2"
					},
					"type": "array"
				},
				"Description": {
					"$ref": "#/definitions/RestrictedFINXMax140Text",
					"type": "string"
				}
			},
			"type": "object"
		},
		"ISINOct2015Identifier" : {
		
			"pattern":"^[A-Z]{2,2}[A-Z0-9]{9,9}[0-9]{1,1}$",
			"type":"string"
		},
		"OtherIdentification2": {
			"additionalProperties": false,
			"properties": {
				"Identification": {
					"$ref": "#/definitions/RestrictedFINXMax31Text",
					"type": "string"
				},
				"Suffix": {
					"$ref": "#/definitions/Max16Text",
					"type": "string"
				},
				"Type": {
					"$ref": "#/definitions/IdentificationSource4Choice",
					"type": "object",
					"additionalProperties": false
				}
			},
			"required": ["Identification","Type"],
			"type": "object"
		},
		"RestrictedFINXMax31Text": {
			"description": "Specifies a character string with a maximum length of 31 characters limited to character set X, that is, a-z A-Z / - ? : ( ) . , ‘ + .",
			"minLength": 1,
			"maxLength": 31,
			"pattern": "^[0-9a-zA-Z/\\-\\?:\\(\\)\\.,'\\+ ]{1,31}$",
			"type": "string"
		},
		"Max16Text": {
			"description": "Specifies a character string with a maximum length of 16 characters.",
			"minLength": 1,
			"maxLength": 16,
			"type": "string"
		},
		"IdentificationSource4Choice": {
			"oneOf":[
				{"required":["Code"]},
				{"required":["Proprietary"]}
			],
			"properties":{
				"Code": {
					"$ref": "#/definitions/ExternalFinancialInstrumentIdentificationType1Code",
					"type": "string"
				},
				"Proprietary": {
					"$ref": "#/definitions/RestrictedFINExact2Text",
					"type": "string"
				}},
			"additionalProperties": false,
			"type": "object"
		},
		"ExternalFinancialInstrumentIdentificationType1Code": {			
			"type": "string"
		},
		"RestrictedFINExact2Text": {
			"description": "Specifies a character string with an exact length of 2 characters that must has a pattern XX|TS.",
			"minLength": 2,
			"maxLength": 2,
			"pattern": "^XX|TS$",
			"type": "string"
		},
		"RestrictedFINXMax140Text": {
			"description": "Specifies a character string with a maximum length of 140 characters limited to character set X, that is, a-z A-Z / - ? : ( ) . , ‘ + .",
			"minLength": 1,
			"maxLength": 140,
			"pattern": "^[0-9a-zA-Z/\\-\\?:\\(\\)\\.\\n\\r,'\\+ ]{1,140}$",
			"type": "string"
		},
		"Quantity10Choice": {
			"oneOf":[
				{"required":["Quantity"]},
				{"required":["OriginalAndCurrentFace"]}
			],
			"properties":{
				"Quantity": {
					"$ref": "#/definitions/FinancialInstrumentQuantity15Choice",
					"type": "object",
					"additionalProperties": false
				},
				"OriginalAndCurrentFace": {
					"$ref": "#/definitions/OriginalAndCurrentQuantities4",
					"type": "object",
					"additionalProperties": false
				}},
			"additionalProperties": false,
			"type": "object"
		},
		"FinancialInstrumentQuantity15Choice": {
			"oneOf":[
				{"required":["Unit"]},
				{"required":["FaceAmount"]},
				{"required":["AmortisedValue"]}
			],
			"properties":{
				"Unit": {
					"$ref": "#/definitions/RestrictedFINDecimalNumber",
					"type": "string"
				},
				"FaceAmount": {
					"$ref": "#/definitions/RestrictedFINImpliedCurrencyAndAmount",
					"type": "string"
				},
				"AmortisedValue": {
					"$ref": "#/definitions/RestrictedFINImpliedCurrencyAndAmount",
					"type": "string"
				}},
			"additionalProperties": false,
			"type": "object"
		},
		"RestrictedFINDecimalNumber" : {
		
			"maxLength":14,
			"type":"string"
		},
		"RestrictedFINImpliedCurrencyAndAmount" : {
			"type": "string",
			"maxLength":14
			
		},
		"OriginalAndCurrentQuantities4": {
			"additionalProperties": false,
			"properties": {
				"FaceAmount": {
					"$ref": "#/definitions/RestrictedFINImpliedCurrencyAndAmount",
					"type": "string"
				},
				"AmortisedValue": {
					"$ref": "#/definitions/RestrictedFINImpliedCurrencyAndAmount",
					"type": "string"
				}
			},
			"required": ["FaceAmount","AmortisedValue"],
			"type": "object"
		},
		"AmountAndDirection67": {
			"additionalProperties": false,
			"properties": {
				"Amount": {
					"$ref": "#/definitions/RestrictedFINActiveCurrencyAndAmount",
					"type": "string"
				},
				"CreditDebitIndicator": {
					"$ref": "#/definitions/CreditDebitCode",
					"type": "string"
				},
				"OriginalCurrencyAndOrderedAmount": {
					"$ref": "#/definitions/RestrictedFINActiveOrHistoricCurrencyAndAmount",
					"type": "string"
				}
			},
			"required": ["Amount","CreditDebitIndicator"],
			"type": "object"
		},
		"RestrictedFINActiveCurrencyAndAmount" : {
			"type":"object",
			"properties":{
				"$": {
					"maxLength":14,
					"type":"string" 
				},
				"ActiveCurrencyCode":{
					"$ref":"#/definitions/ActiveCurrencyCode"
				}
			}
			
		},
		"ActiveCurrencyCode": {
			"pattern": "^[A-Z]{3,3}$",			
			"type": "string"
		},
		"CreditDebitCode": {
			"enum":["DBIT","CRDT"],			
			"type": "string"
		},
		"RestrictedFINActiveOrHistoricCurrencyAndAmount" : {
			"type":"object",
			"properties":{
				"$": {
					"maxLength":14,
					"type":"string" 
				},
				"ActiveOrHistoricCurrencyCode":{
					"$ref":"#/definitions/ActiveOrHistoricCurrencyCode"
				}
			}
			
		},
		"ActiveOrHistoricCurrencyCode": {
			"pattern": "^[A-Z]{3,3}$",			
			"type": "string"
		},
		"AmountAndDirection59": {
			"additionalProperties": false,
			"properties": {
				"Amount": {
					"$ref": "#/definitions/RestrictedFINActiveOrHistoricCurrencyAndAmount",
					"type": "string"
				},
				"CreditDebitIndicator": {
					"$ref": "#/definitions/CreditDebitCode",
					"type": "string"
				}
			},
			"required": ["Amount"],
			"type": "object"
		},
		"SettlementDate32Choice": {
			"oneOf":[
				{"required":["Date"]},
				{"required":["DateCode"]}
			],
			"properties":{
				"Date": {
					"$ref": "#/definitions/DateAndDateTime2Choice",
					"type": "object",
					"additionalProperties": false
				},
				"DateCode": {
					"$ref": "#/definitions/SettlementDateCode11Choice",
					"type": "object",
					"additionalProperties": false
				}},
			"additionalProperties": false,
			"type": "object"
		},
		"DateAndDateTime2Choice": {
			"oneOf":[
				{"required":["Date"]},
				{"required":["DateTime"]}
			],
			"properties":{
				"Date": {
					"$ref": "#/definitions/ISODate",
					"type": "string"
				},
				"DateTime": {
					"$ref": "#/definitions/ISODateTime",
					"type": "string"
				}},
			"additionalProperties": false,
			"type": "object"
		},
		"ISODate" : {
		
			"type":"string"
		},
		"ISODateTime" : {
		
			"type":"string"
		},
		"SettlementDateCode11Choice": {
			"oneOf":[
				{"required":["Code"]},
				{"required":["Proprietary"]}
			],
			"properties":{
				"Code": {
					"$ref": "#/definitions/DateType4Code",
					"type": "string"
				},
				"Proprietary": {
					"$ref": "#/definitions/GenericIdentification47",
					"type": "object",
					"additionalProperties": false
				}},
			"additionalProperties": false,
			"type": "object"
		},
		"DateType4Code": {
			"enum":["OPEN","UKWN"],			
			"type": "string"
		},
		"TerminationDate7Choice": {
			"oneOf":[
				{"required":["Date"]},
				{"required":["Code"]}
			],
			"properties":{
				"Date": {
					"$ref": "#/definitions/DateAndDateTime2Choice",
					"type": "object",
					"additionalProperties": false
				},
				"Code": {
					"$ref": "#/definitions/DateCode32Choice",
					"type": "object",
					"additionalProperties": false
				}},
			"additionalProperties": false,
			"type": "object"
		},
		"DateCode32Choice": {
			"oneOf":[
				{"required":["Code"]},
				{"required":["Proprietary"]}
			],
			"properties":{
				"Code": {
					"$ref": "#/definitions/DateType5Code",
					"type": "string"
				},
				"Proprietary": {
					"$ref": "#/definitions/GenericIdentification47",
					"type": "object",
					"additionalProperties": false
				}},
			"additionalProperties": false,
			"type": "object"
		},
		"DateType5Code": {
			"enum":["OPEN"],			
			"type": "string"
		},
		"TradeDate9Choice": {
			"oneOf":[
				{"required":["Date"]},
				{"required":["DateCode"]}
			],
			"properties":{
				"Date": {
					"$ref": "#/definitions/DateAndDateTime2Choice",
					"type": "object",
					"additionalProperties": false
				},
				"DateCode": {
					"$ref": "#/definitions/TradeDateCode4Choice",
					"type": "object",
					"additionalProperties": false
				}},
			"additionalProperties": false,
			"type": "object"
		},
		"TradeDateCode4Choice": {
			"oneOf":[
				{"required":["Code"]},
				{"required":["Proprietary"]}
			],
			"properties":{
				"Code": {
					"$ref": "#/definitions/DateType3Code",
					"type": "string"
				},
				"Proprietary": {
					"$ref": "#/definitions/GenericIdentification47",
					"type": "object",
					"additionalProperties": false
				}},
			"additionalProperties": false,
			"type": "object"
		},
		"DateType3Code": {
			"enum":["VARI"],			
			"type": "string"
		},
		"SecuritiesFinancingTransactionType2Code": {
			"enum":["BSBK","REPU","RVPO","SBBK","SECB","SECL"],			
			"type": "string"
		},
		"ReceiveDelivery1Code": {
			"enum":["DELI","RECE"],			
			"type": "string"
		},
		"DeliveryReceiptType2Code": {
			"enum":["FREE","APMT"],			
			"type": "string"
		},
		"SettlementDetails173": {
			"additionalProperties": false,
			"properties": {
				"HoldIndicator": {
					"$ref": "#/definitions/YesNoIndicator",
					"type": "string"
				},
				"SettlementTransactionCondition": {
					"items": {
						"$ref": "#/definitions/SettlementTransactionCondition22Choice"
					},
					"type": "array"
				},
				"SettlingCapacity": {
					"$ref": "#/definitions/SettlingCapacity8Choice",
					"type": "object",
					"additionalProperties": false
				},
				"StampDutyTaxBasis": {
					"$ref": "#/definitions/GenericIdentification47",
					"type": "object",
					"additionalProperties": false
				},
				"SecuritiesRTGS": {
					"$ref": "#/definitions/SecuritiesRTGS5Choice",
					"type": "object",
					"additionalProperties": false
				},
				"BeneficialOwnership": {
					"$ref": "#/definitions/BeneficialOwnership5Choice",
					"type": "object",
					"additionalProperties": false
				},
				"CashClearingSystem": {
					"$ref": "#/definitions/CashSettlementSystem5Choice",
					"type": "object",
					"additionalProperties": false
				},
				"TaxCapacity": {
					"$ref": "#/definitions/TaxCapacityParty5Choice",
					"type": "object",
					"additionalProperties": false
				},
				"MarketClientSide": {
					"$ref": "#/definitions/MarketClientSide7Choice",
					"type": "object",
					"additionalProperties": false
				},
				"BlockTrade": {
					"$ref": "#/definitions/BlockTrade5Choice",
					"type": "object",
					"additionalProperties": false
				},
				"LegalRestrictions": {
					"$ref": "#/definitions/Restriction6Choice",
					"type": "object",
					"additionalProperties": false
				},
				"SettlementSystemMethod": {
					"$ref": "#/definitions/SettlementSystemMethod5Choice",
					"type": "object",
					"additionalProperties": false
				},
				"NettingEligibility": {
					"$ref": "#/definitions/NettingEligibility5Choice",
					"type": "object",
					"additionalProperties": false
				},
				"CCPEligibility": {
					"$ref": "#/definitions/CentralCounterPartyEligibility5Choice",
					"type": "object",
					"additionalProperties": false
				},
				"PartialSettlementIndicator": {
					"$ref": "#/definitions/SettlementTransactionCondition5Code",
					"type": "string"
				},
				"EligibleForCollateral": {
					"$ref": "#/definitions/YesNoIndicator",
					"type": "string"
				}
			},
			"type": "object"
		},
		"YesNoIndicator" : {
		
				
			"type":"boolean"
		},
		"SettlementTransactionCondition22Choice": {
			"oneOf":[
				{"required":["Code"]},
				{"required":["Proprietary"]}
			],
			"properties":{
				"Code": {
					"$ref": "#/definitions/SettlementTransactionCondition6Code",
					"type": "string"
				},
				"Proprietary": {
					"$ref": "#/definitions/GenericIdentification47",
					"type": "object",
					"additionalProperties": false
				}},
			"additionalProperties": false,
			"type": "object"
		},
		"SettlementTransactionCondition6Code": {
			"enum":["ASGN","BUTC","CLEN","DIRT","DLWM","DRAW","EXER","FRCL","KNOC","PHYS","RESI","SHOR","SPDL","SPST","UNEX","EXPI","PENS","TRIP","NOMC","TRAN","RHYP","ADEA"],			
			"type": "string"
		},
		"SettlingCapacity8Choice": {
			"oneOf":[
				{"required":["Code"]},
				{"required":["Proprietary"]}
			],
			"properties":{
				"Code": {
					"$ref": "#/definitions/SettlingCapacity2Code",
					"type": "string"
				},
				"Proprietary": {
					"$ref": "#/definitions/GenericIdentification47",
					"type": "object",
					"additionalProperties": false
				}},
			"additionalProperties": false,
			"type": "object"
		},
		"SettlingCapacity2Code": {
			"enum":["CUST","SAGE","SPRI","RISP"],			
			"type": "string"
		},
		"SecuritiesRTGS5Choice": {
			"oneOf":[
				{"required":["Indicator"]},
				{"required":["Proprietary"]}
			],
			"properties":{
				"Indicator": {
					"$ref": "#/definitions/YesNoIndicator",
					"type": "string"
				},
				"Proprietary": {
					"$ref": "#/definitions/GenericIdentification47",
					"type": "object",
					"additionalProperties": false
				}},
			"additionalProperties": false,
			"type": "object"
		},
		"BeneficialOwnership5Choice": {
			"oneOf":[
				{"required":["Indicator"]},
				{"required":["Proprietary"]}
			],
			"properties":{
				"Indicator": {
					"$ref": "#/definitions/YesNoIndicator",
					"type": "string"
				},
				"Proprietary": {
					"$ref": "#/definitions/GenericIdentification47",
					"type": "object",
					"additionalProperties": false
				}},
			"additionalProperties": false,
			"type": "object"
		},
		"CashSettlementSystem5Choice": {
			"oneOf":[
				{"required":["Code"]},
				{"required":["Proprietary"]}
			],
			"properties":{
				"Code": {
					"$ref": "#/definitions/CashSettlementSystem2Code",
					"type": "string"
				},
				"Proprietary": {
					"$ref": "#/definitions/GenericIdentification47",
					"type": "object",
					"additionalProperties": false
				}},
			"additionalProperties": false,
			"type": "object"
		},
		"CashSettlementSystem2Code": {
			"enum":["GROS","NETS"],			
			"type": "string"
		},
		"TaxCapacityParty5Choice": {
			"oneOf":[
				{"required":["Code"]},
				{"required":["Proprietary"]}
			],
			"properties":{
				"Code": {
					"$ref": "#/definitions/TaxLiability1Code",
					"type": "string"
				},
				"Proprietary": {
					"$ref": "#/definitions/GenericIdentification47",
					"type": "object",
					"additionalProperties": false
				}},
			"additionalProperties": false,
			"type": "object"
		},
		"TaxLiability1Code": {
			"enum":["PRIN","AGEN"],			
			"type": "string"
		},
		"MarketClientSide7Choice": {
			"oneOf":[
				{"required":["Code"]},
				{"required":["Proprietary"]}
			],
			"properties":{
				"Code": {
					"$ref": "#/definitions/MarketClientSide1Code",
					"type": "string"
				},
				"Proprietary": {
					"$ref": "#/definitions/GenericIdentification47",
					"type": "object",
					"additionalProperties": false
				}},
			"additionalProperties": false,
			"type": "object"
		},
		"MarketClientSide1Code": {
			"enum":["MAKT","CLNT"],			
			"type": "string"
		},
		"BlockTrade5Choice": {
			"oneOf":[
				{"required":["Code"]},
				{"required":["Proprietary"]}
			],
			"properties":{
				"Code": {
					"$ref": "#/definitions/BlockTrade1Code",
					"type": "string"
				},
				"Proprietary": {
					"$ref": "#/definitions/GenericIdentification47",
					"type": "object",
					"additionalProperties": false
				}},
			"additionalProperties": false,
			"type": "object"
		},
		"BlockTrade1Code": {
			"enum":["BLPA","BLCH"],			
			"type": "string"
		},
		"Restriction6Choice": {
			"oneOf":[
				{"required":["Code"]},
				{"required":["Proprietary"]}
			],
			"properties":{
				"Code": {
					"$ref": "#/definitions/OwnershipLegalRestrictions1Code",
					"type": "string"
				},
				"Proprietary": {
					"$ref": "#/definitions/GenericIdentification47",
					"type": "object",
					"additionalProperties": false
				}},
			"additionalProperties": false,
			"type": "object"
		},
		"OwnershipLegalRestrictions1Code": {
			"enum":["A144","NRST","RSTR"],			
			"type": "string"
		},
		"SettlementSystemMethod5Choice": {
			"oneOf":[
				{"required":["Code"]},
				{"required":["Proprietary"]}
			],
			"properties":{
				"Code": {
					"$ref": "#/definitions/SettlementSystemMethod1Code",
					"type": "string"
				},
				"Proprietary": {
					"$ref": "#/definitions/GenericIdentification47",
					"type": "object",
					"additionalProperties": false
				}},
			"additionalProperties": false,
			"type": "object"
		},
		"SettlementSystemMethod1Code": {
			"enum":["NSET","YSET"],			
			"type": "string"
		},
		"NettingEligibility5Choice": {
			"oneOf":[
				{"required":["Indicator"]},
				{"required":["Proprietary"]}
			],
			"properties":{
				"Indicator": {
					"$ref": "#/definitions/YesNoIndicator",
					"type": "string"
				},
				"Proprietary": {
					"$ref": "#/definitions/GenericIdentification47",
					"type": "object",
					"additionalProperties": false
				}},
			"additionalProperties": false,
			"type": "object"
		},
		"CentralCounterPartyEligibility5Choice": {
			"oneOf":[
				{"required":["Indicator"]},
				{"required":["Proprietary"]}
			],
			"properties":{
				"Indicator": {
					"$ref": "#/definitions/YesNoIndicator",
					"type": "string"
				},
				"Proprietary": {
					"$ref": "#/definitions/GenericIdentification47",
					"type": "object",
					"additionalProperties": false
				}},
			"additionalProperties": false,
			"type": "object"
		},
		"SettlementTransactionCondition5Code": {
			"enum":["PART","NPAR","PARC","PARQ"],			
			"type": "string"
		},
		"RateType67Choice": {
			"oneOf":[
				{"required":["Code"]},
				{"required":["Proprietary"]}
			],
			"properties":{
				"Code": {
					"$ref": "#/definitions/RateType1Code",
					"type": "string"
				},
				"Proprietary": {
					"$ref": "#/definitions/GenericIdentification47",
					"type": "object",
					"additionalProperties": false
				}},
			"additionalProperties": false,
			"type": "object"
		},
		"RateType1Code": {
			"enum":["FIXE","FORF","VARI"],			
			"type": "string"
		},
		"RateName2": {
			"additionalProperties": false,
			"properties": {
				"Issuer": {
					"$ref": "#/definitions/RestrictedFINXMax8Text",
					"type": "string"
				},
				"RateName": {
					"$ref": "#/definitions/RestrictedFINXMax24Text",
					"type": "string"
				}
			},
			"required": ["RateName"],
			"type": "object"
		},
		"RestrictedFINXMax8Text": {
			"description": "Specifies a character string with a maximum length of 8 characters limited to character set X, that is, a-z A-Z / - ? : ( ) . , ‘ + .",
			"minLength": 1,
			"maxLength": 8,
			"pattern": "^[0-9a-zA-Z/\\-\\?:\\(\\)\\.,'\\+ ]{1,8}$",
			"type": "string"
		},
		"RestrictedFINXMax24Text": {
			"description": "Specifies a character string with a maximum length of 24 characters. It has a pattern that disables the use of characters that is not part of the character set X, that is, that is not a-z A-Z / - ? : ( ) . , ‘ + , and disable the use of slash \"/\" at the beginning and end of line and double slash \"//\" within the line.",
			"minLength": 1,
			"maxLength": 24,
			"pattern": "^([0-9a-zA-Z\\-\\?:\\(\\)\\.,'\\+ ]([0-9a-zA-Z\\-\\?:\\(\\)\\.,'\\+ ]*(/[0-9a-zA-Z\\-\\?:\\(\\)\\.,'\\+ ])?)*)$",
			"type": "string"
		},
		"Rate2": {
			"additionalProperties": false,
			"properties": {
				"Sign": {
					"$ref": "#/definitions/PlusOrMinusIndicator",
					"type": "string"
				},
				"Rate": {
					"$ref": "#/definitions/PercentageRate",
					"type": "string"
				}
			},
			"required": ["Rate"],
			"type": "object"
		},
		"PlusOrMinusIndicator" : {
		
				
			"type":"boolean"
		},
		"PercentageRate" : {
		
			"maxLength":11,
			"type":"string"
		},
		"RateOrName2Choice": {
			"oneOf":[
				{"required":["Rate"]},
				{"required":["RateName"]}
			],
			"properties":{
				"Rate": {
					"$ref": "#/definitions/Rate2",
					"type": "object",
					"additionalProperties": false
				},
				"RateName": {
					"$ref": "#/definitions/RateName2",
					"type": "object",
					"additionalProperties": false
				}},
			"additionalProperties": false,
			"type": "object"
		},
		"SettlementParties83": {
			"additionalProperties": false,
			"properties": {
				"Depository": {
					"$ref": "#/definitions/PartyIdentification162",
					"type": "object",
					"additionalProperties": false
				},
				"Party1": {
					"$ref": "#/definitions/PartyIdentificationAndAccount188",
					"type": "object",
					"additionalProperties": false
				},
				"Party2": {
					"$ref": "#/definitions/PartyIdentificationAndAccount188",
					"type": "object",
					"additionalProperties": false
				},
				"Party3": {
					"$ref": "#/definitions/PartyIdentificationAndAccount188",
					"type": "object",
					"additionalProperties": false
				},
				"Party4": {
					"$ref": "#/definitions/PartyIdentificationAndAccount188",
					"type": "object",
					"additionalProperties": false
				},
				"Party5": {
					"$ref": "#/definitions/PartyIdentificationAndAccount188",
					"type": "object",
					"additionalProperties": false
				}
			},
			"type": "object"
		},
		"PartyIdentification162": {
			"additionalProperties": false,
			"properties": {
				"Identification": {
					"$ref": "#/definitions/PartyIdentification145Choice",
					"type": "object",
					"additionalProperties": false
				},
				"LEI": {
					"$ref": "#/definitions/LEIIdentifier",
					"type": "string"
				},
				"AlternateIdentification": {
					"$ref": "#/definitions/AlternatePartyIdentification9",
					"type": "object",
					"additionalProperties": false
				},
				"ProcessingDate": {
					"$ref": "#/definitions/DateAndDateTime2Choice",
					"type": "object",
					"additionalProperties": false
				},
				"ProcessingIdentification": {
					"$ref": "#/definitions/RestrictedFINXMax16Text",
					"type": "string"
				},
				"AdditionalInformation": {
					"$ref": "#/definitions/PartyTextInformation3",
					"type": "object",
					"additionalProperties": false
				}
			},
			"required": ["Identification"],
			"type": "object"
		},
		"PartyIdentification145Choice": {
			"oneOf":[
				{"required":["AnyBIC"]},
				{"required":["NameAndAddress"]},
				{"required":["Country"]}
			],
			"properties":{
				"AnyBIC": {
					"$ref": "#/definitions/AnyBICDec2014Identifier",
					"type": "string"
				},
				"NameAndAddress": {
					"$ref": "#/definitions/NameAndAddress12",
					"type": "object",
					"additionalProperties": false
				},
				"Country": {
					"$ref": "#/definitions/CountryCode",
					"type": "string"
				}},
			"additionalProperties": false,
			"type": "object"
		},
		"NameAndAddress12": {
			"additionalProperties": false,
			"properties": {
				"Name": {
					"$ref": "#/definitions/RestrictedFINXMax140Text",
					"type": "string"
				}
			},
			"required": ["Name"],
			"type": "object"
		},
		"AlternatePartyIdentification9": {
			"additionalProperties": false,
			"properties": {
				"IdentificationType": {
					"$ref": "#/definitions/IdentificationType44Choice",
					"type": "object",
					"additionalProperties": false
				},
				"Country": {
					"$ref": "#/definitions/CountryCode",
					"type": "string"
				},
				"AlternateIdentification": {
					"$ref": "#/definitions/RestrictedFINXMax30Text",
					"type": "string"
				}
			},
			"required": ["IdentificationType","Country","AlternateIdentification"],
			"type": "object"
		},
		"IdentificationType44Choice": {
			"oneOf":[
				{"required":["Code"]},
				{"required":["Proprietary"]}
			],
			"properties":{
				"Code": {
					"$ref": "#/definitions/TypeOfIdentification1Code",
					"type": "string"
				},
				"Proprietary": {
					"$ref": "#/definitions/GenericIdentification47",
					"type": "object",
					"additionalProperties": false
				}},
			"additionalProperties": false,
			"type": "object"
		},
		"TypeOfIdentification1Code": {
			"enum":["ARNU","CCPT","CHTY","CORP","DRLC","FIIN","TXID"],			
			"type": "string"
		},
		"PartyTextInformation3": {
			"additionalProperties": false,
			"properties": {
				"DeclarationDetails": {
					"$ref": "#/definitions/RestrictedFINXMax350Text",
					"type": "string"
				},
				"PartyContactDetails": {
					"$ref": "#/definitions/RestrictedFINXMax140Text",
					"type": "string"
				},
				"RegistrationDetails": {
					"$ref": "#/definitions/RestrictedFINXMax350Text",
					"type": "string"
				}
			},
			"type": "object"
		},
		"RestrictedFINXMax350Text": {
			"description": "Specifies a character string with a maximum length of 350 characters limited to character set X, that is, a-z A-Z / - ? : ( ) . , ‘ + .",
			"minLength": 1,
			"maxLength": 350,
			"pattern": "^[0-9a-zA-Z/\\-\\?:\\(\\)\\.\\n\\r,'\\+ ]{1,350}$",
			"type": "string"
		},
		"PartyIdentificationAndAccount188": {
			"additionalProperties": false,
			"properties": {
				"Identification": {
					"$ref": "#/definitions/PartyIdentification137Choice",
					"type": "object",
					"additionalProperties": false
				},
				"LEI": {
					"$ref": "#/definitions/LEIIdentifier",
					"type": "string"
				},
				"AlternateIdentification": {
					"$ref": "#/definitions/AlternatePartyIdentification9",
					"type": "object",
					"additionalProperties": false
				},
				"SafekeepingAccount": {
					"$ref": "#/definitions/SecuritiesAccount37",
					"type": "object",
					"additionalProperties": false
				},
				"ProcessingDate": {
					"$ref": "#/definitions/DateAndDateTime2Choice",
					"type": "object",
					"additionalProperties": false
				},
				"ProcessingIdentification": {
					"$ref": "#/definitions/RestrictedFINXMax16Text",
					"type": "string"
				},
				"AdditionalInformation": {
					"$ref": "#/definitions/PartyTextInformation3",
					"type": "object",
					"additionalProperties": false
				}
			},
			"required": ["Identification"],
			"type": "object"
		},
		"PartyIdentification137Choice": {
			"oneOf":[
				{"required":["AnyBIC"]},
				{"required":["ProprietaryIdentification"]},
				{"required":["NameAndAddress"]}
			],
			"properties":{
				"AnyBIC": {
					"$ref": "#/definitions/AnyBICDec2014Identifier",
					"type": "string"
				},
				"ProprietaryIdentification": {
					"$ref": "#/definitions/GenericIdentification84",
					"type": "object",
					"additionalProperties": false
				},
				"NameAndAddress": {
					"$ref": "#/definitions/NameAndAddress12",
					"type": "object",
					"additionalProperties": false
				}},
			"additionalProperties": false,
			"type": "object"
		},
		"SecuritiesAccount37": {
			"additionalProperties": false,
			"properties": {
				"Identification": {
					"$ref": "#/definitions/RestrictedFINXMax35Text",
					"type": "string"
				},
				"Type": {
					"$ref": "#/definitions/GenericIdentification47",
					"type": "object",
					"additionalProperties": false
				},
				"Name": {
					"$ref": "#/definitions/Max70Text",
					"type": "string"
				}
			},
			"required": ["Identification"],
			"type": "object"
		},
		"PartyIdentification170": {
			"additionalProperties": false,
			"properties": {
				"Identification": {
					"$ref": "#/definitions/PartyIdentification176Choice",
					"type": "object",
					"additionalProperties": false
				},
				"LEI": {
					"$ref": "#/definitions/LEIIdentifier",
					"type": "string"
				}
			},
			"required": ["Identification"],
			"type": "object"
		},
		"PartyIdentification176Choice": {
			"oneOf":[
				{"required":["AnyBIC"]},
				{"required":["ProprietaryIdentification"]},
				{"required":["NameAndAddress"]},
				{"required":["Country"]}
			],
			"properties":{
				"AnyBIC": {
					"$ref": "#/definitions/AnyBICDec2014Identifier",
					"type": "string"
				},
				"ProprietaryIdentification": {
					"$ref": "#/definitions/GenericIdentification84",
					"type": "object",
					"additionalProperties": false
				},
				"NameAndAddress": {
					"$ref": "#/definitions/NameAndAddress12",
					"type": "object",
					"additionalProperties": false
				},
				"Country": {
					"$ref": "#/definitions/CountryCode",
					"type": "string"
				}},
			"additionalProperties": false,
			"type": "object"
		},
		"SupplementaryData1": {
			"additionalProperties": false,
			"properties": {
				"PlaceAndName": {
					"$ref": "#/definitions/Max350Text",
					"type": "string"
				},
				"Envelope": {
					"$ref": "#/definitions/SupplementaryDataEnvelope1",
					"type": "object",
					"additionalProperties": false
				}
			},
			"required": ["Envelope"],
			"type": "object"
		},
		"Max350Text": {
			"description": "Specifies a character string with a maximum length of 350 characters.",
			"minLength": 1,
			"maxLength": 350,
			"type": "string"
		},
		"SupplementaryDataEnvelope1" : {
		
			"type":"object"
		},
		"SecuritiesFinancingStatusAdvice002V08":{
			"additionalProperties": false,
			"properties": {
		
				"TransactionIdentification": {
					"$ref": "#/definitions/TransactionIdentifications35",
					"type": "object",
					"additionalProperties": false
				},
				"ProcessingStatus": {
					"$ref": "#/definitions/ProcessingStatus57Choice",
					"type": "object",
					"additionalProperties": false
				},
				"MatchingStatus": {
					"$ref": "#/definitions/MatchingStatus29Choice",
					"type": "object",
					"additionalProperties": false
				},
				"InferredMatchingStatus": {
					"$ref": "#/definitions/MatchingStatus29Choice",
					"type": "object",
					"additionalProperties": false
				},
				"SettlementStatus": {
					"$ref": "#/definitions/SettlementStatus21Choice",
					"type": "object",
					"additionalProperties": false
				},
				"RepoCallRequestStatus": {
					"$ref": "#/definitions/RepoCallRequestStatus9Choice",
					"type": "object",
					"additionalProperties": false
				},
				"TransactionDetails": {
					"$ref": "#/definitions/SecuritiesFinancingTransactionDetails49",
					"type": "object",
					"additionalProperties": false
				},
				"SupplementaryData": {
					"items": {
						"$ref": "#/definitions/SupplementaryData1"
					},
					"type": "array"
				}
			},
			"required": [
		"TransactionIdentification"],
			"type": "object"
		}
	},
	"properties": {
	    "@xmlns": {
			"default": "urn:iso:std:iso:20022:tech:json:sese.034.002.08"
		},
		"Securities_Financing_Status_Advice002": {
			"$ref": "#/definitions/SecuritiesFinancingStatusAdvice002V08"
		}
	},
	"type": "object"
}
