{

	"$schema": "http://json-schema.org/draft-04/schema#",
	"description": "This is the ISO/TS 23029:2019 json schema for the message definition seev.036.001.05-CorporateActionMovementConfirmationV05.\nAll rights reserved. Generated by https://ISO20022.plus/ from eRepository on https://ISO20022.org/. Without warranty.",
	"additionalProperties": false,
	"definitions": {
				
		
		"DocumentIdentification15": {
			"additionalProperties": false,
			"properties": {
				"Identification": {
					"$ref": "#/definitions/Max35Text",
					"type": "string"
				},
				"LinkageType": {
					"$ref": "#/definitions/ProcessingPosition1Choice",
					"type": "object",
					"additionalProperties": false
				}
			},
			"required": ["Identification"],
			"type": "object"
		},
		"Max35Text": {
			"description": "Specifies a character string with a maximum length of 35 characters.",
			"minLength": 1,
			"maxLength": 35,
			"type": "string"
		},
		"ProcessingPosition1Choice": {
			"oneOf":[
				{"required":["Code"]},
				{"required":["Proprietary"]}
			],
			"properties":{
				"Code": {
					"$ref": "#/definitions/ProcessingPosition3Code",
					"type": "string"
				},
				"Proprietary": {
					"$ref": "#/definitions/GenericIdentification20",
					"type": "object",
					"additionalProperties": false
				}},
			"additionalProperties": false,
			"type": "object"
		},
		"ProcessingPosition3Code": {
			"enum":["AFTE","WITH","BEFO","INFO"],			
			"type": "string"
		},
		"GenericIdentification20": {
			"additionalProperties": false,
			"properties": {
				"Identification": {
					"$ref": "#/definitions/Exact4AlphaNumericText",
					"type": "string"
				},
				"Issuer": {
					"$ref": "#/definitions/Max35Text",
					"type": "string"
				},
				"SchemeName": {
					"$ref": "#/definitions/Max35Text",
					"type": "string"
				}
			},
			"required": ["Identification","Issuer"],
			"type": "object"
		},
		"Exact4AlphaNumericText": {
			"description": "Specifies an alphanumeric string with a length of 4 characters.",
			"pattern": "^[a-zA-Z0-9]{4}$",
			"type": "string"
		},
		"DocumentIdentification9": {
			"additionalProperties": false,
			"properties": {
				"Identification": {
					"$ref": "#/definitions/Max35Text",
					"type": "string"
				}
			},
			"required": ["Identification"],
			"type": "object"
		},
		"DocumentIdentification13": {
			"additionalProperties": false,
			"properties": {
				"Identification": {
					"$ref": "#/definitions/DocumentIdentification1Choice",
					"type": "object",
					"additionalProperties": false
				},
				"DocumentNumber": {
					"$ref": "#/definitions/DocumentNumber1Choice",
					"type": "object",
					"additionalProperties": false
				},
				"LinkageType": {
					"$ref": "#/definitions/ProcessingPosition1Choice",
					"type": "object",
					"additionalProperties": false
				}
			},
			"required": ["Identification"],
			"type": "object"
		},
		"DocumentIdentification1Choice": {
			"oneOf":[
				{"required":["AccountServicerDocumentIdentification"]},
				{"required":["AccountOwnerDocumentIdentification"]}
			],
			"properties":{
				"AccountServicerDocumentIdentification": {
					"$ref": "#/definitions/Max35Text",
					"type": "string"
				},
				"AccountOwnerDocumentIdentification": {
					"$ref": "#/definitions/Max35Text",
					"type": "string"
				}},
			"additionalProperties": false,
			"type": "object"
		},
		"DocumentNumber1Choice": {
			"oneOf":[
				{"required":["ShortNumber"]},
				{"required":["LongNumber"]},
				{"required":["ProprietaryNumber"]}
			],
			"properties":{
				"ShortNumber": {
					"$ref": "#/definitions/Exact3NumericText",
					"type": "string"
				},
				"LongNumber": {
					"$ref": "#/definitions/ISO20022MessageIdentificationText",
					"type": "string"
				},
				"ProprietaryNumber": {
					"$ref": "#/definitions/GenericIdentification19",
					"type": "object",
					"additionalProperties": false
				}},
			"additionalProperties": false,
			"type": "object"
		},
		"Exact3NumericText": {
			"description": "Specifies a numeric string with an exact length of 3 digits.",
			"pattern": "^[0-9]{3}$",
			"type": "string"
		},
		"ISO20022MessageIdentificationText": {
			"description": "ISO 20022 Message identifier of an MX message.",
			"pattern": "^[a-z]{4}\\.[0-9]{3}\\.[0-9]{3}\\.[0-9]{2}$",
			"type": "string"
		},
		"GenericIdentification19": {
			"additionalProperties": false,
			"properties": {
				"Identification": {
					"$ref": "#/definitions/Max35Text",
					"type": "string"
				},
				"Issuer": {
					"$ref": "#/definitions/Max35Text",
					"type": "string"
				},
				"SchemeName": {
					"$ref": "#/definitions/Max35Text",
					"type": "string"
				}
			},
			"required": ["Identification","Issuer"],
			"type": "object"
		},
		"CorporateActionEventReference1": {
			"additionalProperties": false,
			"properties": {
				"EventIdentification": {
					"$ref": "#/definitions/CorporateActionEventReference1Choice",
					"type": "object",
					"additionalProperties": false
				},
				"LinkageType": {
					"$ref": "#/definitions/ProcessingPosition1Choice",
					"type": "object",
					"additionalProperties": false
				}
			},
			"required": ["EventIdentification"],
			"type": "object"
		},
		"CorporateActionEventReference1Choice": {
			"oneOf":[
				{"required":["LinkedOfficialCorporateActionEventIdentification"]},
				{"required":["LinkedCorporateActionIdentification"]}
			],
			"properties":{
				"LinkedOfficialCorporateActionEventIdentification": {
					"$ref": "#/definitions/Max35Text",
					"type": "string"
				},
				"LinkedCorporateActionIdentification": {
					"$ref": "#/definitions/Max35Text",
					"type": "string"
				}},
			"additionalProperties": false,
			"type": "object"
		},
		"CorporateActionGeneralInformation50": {
			"additionalProperties": false,
			"properties": {
				"CorporateActionEventIdentification": {
					"$ref": "#/definitions/Max35Text",
					"type": "string"
				},
				"OfficialCorporateActionEventIdentification": {
					"$ref": "#/definitions/Max35Text",
					"type": "string"
				},
				"ClassActionNumber": {
					"$ref": "#/definitions/Max35Text",
					"type": "string"
				},
				"EventType": {
					"$ref": "#/definitions/CorporateActionEventType12Choice",
					"type": "object",
					"additionalProperties": false
				},
				"FinancialInstrumentIdentification": {
					"$ref": "#/definitions/SecurityIdentification14",
					"type": "object",
					"additionalProperties": false
				},
				"AdditionalBusinessProcessIndicator": {
					"$ref": "#/definitions/AdditionalBusinessProcessFormat7Choice",
					"type": "object",
					"additionalProperties": false
				},
				"IntermediateSecuritiesDistributionType": {
					"$ref": "#/definitions/IntermediateSecuritiesDistributionTypeFormat6Choice",
					"type": "object",
					"additionalProperties": false
				},
				"FractionalQuantity": {
					"$ref": "#/definitions/FinancialInstrumentQuantity1Choice",
					"type": "object",
					"additionalProperties": false
				}
			},
			"required": ["CorporateActionEventIdentification","EventType","FinancialInstrumentIdentification"],
			"type": "object"
		},
		"CorporateActionEventType12Choice": {
			"oneOf":[
				{"required":["Code"]},
				{"required":["Proprietary"]}
			],
			"properties":{
				"Code": {
					"$ref": "#/definitions/CorporateActionEventType11Code",
					"type": "string"
				},
				"Proprietary": {
					"$ref": "#/definitions/GenericIdentification20",
					"type": "object",
					"additionalProperties": false
				}},
			"additionalProperties": false,
			"type": "object"
		},
		"CorporateActionEventType11Code": {
			"enum":["DRIP","CAPG","DVCA","DVOP","DVSE","LIQU","MRGR","SOFF","TEND","BONU","CHAN","REDO","EXOF","DECR","REDM","INTR","PDEF","ATTI","CONV","DETI","ACTV","BRUP","DFLT","EXRI","CAPI","CONS","COOP","DSCL","DRAW","DTCH","MCAL","INCR","PPMT","PRII","RHDI","EXTM","CERT","ODLT","OTHR","PARI","PCAL","PRED","PINK","PLAC","PRIO","BPUT","REMK","BIDS","SPLR","RHTS","DVSC","SHPR","SMAL","SPLF","TREC","DLST","SUSP","EXWA","WTRC","WRTH","CLSA","CAPD","CREV","MTNG","DRCA","ACCU","NOOF"],			
			"type": "string"
		},
		"SecurityIdentification14": {
			"additionalProperties": false,
			"properties": {
				"ISIN": {
					"$ref": "#/definitions/ISINIdentifier",
					"type": "string"
				},
				"OtherIdentification": {
					"items": {
						"$ref": "#/definitions/OtherIdentification1"
					},
					"type": "array"
				},
				"Description": {
					"$ref": "#/definitions/Max140Text",
					"type": "string"
				}
			},
			"type": "object"
		},
		"ISINIdentifier" : {
		
			"pattern":"^[A-Z0-9]{12,12}$",
			"type":"string"
		},
		"OtherIdentification1": {
			"additionalProperties": false,
			"properties": {
				"Identification": {
					"$ref": "#/definitions/Max35Text",
					"type": "string"
				},
				"Suffix": {
					"$ref": "#/definitions/Max16Text",
					"type": "string"
				},
				"Type": {
					"$ref": "#/definitions/IdentificationSource3Choice",
					"type": "object",
					"additionalProperties": false
				}
			},
			"required": ["Identification","Type"],
			"type": "object"
		},
		"Max16Text": {
			"description": "Specifies a character string with a maximum length of 16 characters.",
			"minLength": 1,
			"maxLength": 16,
			"type": "string"
		},
		"IdentificationSource3Choice": {
			"oneOf":[
				{"required":["Code"]},
				{"required":["Proprietary"]}
			],
			"properties":{
				"Code": {
					"$ref": "#/definitions/ExternalFinancialInstrumentIdentificationType1Code",
					"type": "string"
				},
				"Proprietary": {
					"$ref": "#/definitions/Max35Text",
					"type": "string"
				}},
			"additionalProperties": false,
			"type": "object"
		},
		"ExternalFinancialInstrumentIdentificationType1Code": {			
			"type": "string"
		},
		"Max140Text": {
			"description": "Specifies a character string with a maximum length of 140 characters.",
			"minLength": 1,
			"maxLength": 140,
			"type": "string"
		},
		"AdditionalBusinessProcessFormat7Choice": {
			"oneOf":[
				{"required":["Code"]},
				{"required":["Proprietary"]}
			],
			"properties":{
				"Code": {
					"$ref": "#/definitions/AdditionalBusinessProcess4Code",
					"type": "string"
				},
				"Proprietary": {
					"$ref": "#/definitions/GenericIdentification20",
					"type": "object",
					"additionalProperties": false
				}},
			"additionalProperties": false,
			"type": "object"
		},
		"AdditionalBusinessProcess4Code": {
			"enum":["ACLA","ATXF","CNTR","NAMC","NPLE","SCHM","CLAI","TAXR","CONS"],			
			"type": "string"
		},
		"IntermediateSecuritiesDistributionTypeFormat6Choice": {
			"oneOf":[
				{"required":["Code"]},
				{"required":["Proprietary"]}
			],
			"properties":{
				"Code": {
					"$ref": "#/definitions/IntermediateSecurityDistributionType4Code",
					"type": "string"
				},
				"Proprietary": {
					"$ref": "#/definitions/GenericIdentification20",
					"type": "object",
					"additionalProperties": false
				}},
			"additionalProperties": false,
			"type": "object"
		},
		"IntermediateSecurityDistributionType4Code": {
			"enum":["BIDS","BONU","DRIP","DVCA","DVOP","EXRI","PRIO","DVSC","DVSE","INTR","LIQU","SOFF","SPLF","EXOF"],			
			"type": "string"
		},
		"FinancialInstrumentQuantity1Choice": {
			"oneOf":[
				{"required":["Unit"]},
				{"required":["FaceAmount"]},
				{"required":["AmortisedValue"]}
			],
			"properties":{
				"Unit": {
					"$ref": "#/definitions/DecimalNumber",
					"type": "string"
				},
				"FaceAmount": {
					"$ref": "#/definitions/ImpliedCurrencyAndAmount",
					"type": "string"
				},
				"AmortisedValue": {
					"$ref": "#/definitions/ImpliedCurrencyAndAmount",
					"type": "string"
				}},
			"additionalProperties": false,
			"type": "object"
		},
		"DecimalNumber" : {
		
			"maxLength":18,
			"type":"string"
		},
		"ImpliedCurrencyAndAmount" : {
			"type": "string",
			"maxLength":18
			
		},
		"AccountAndBalance26": {
			"additionalProperties": false,
			"properties": {
				"SafekeepingAccount": {
					"$ref": "#/definitions/Max35Text",
					"type": "string"
				},
				"AccountOwner": {
					"$ref": "#/definitions/PartyIdentification36Choice",
					"type": "object",
					"additionalProperties": false
				},
				"SafekeepingPlace": {
					"$ref": "#/definitions/SafekeepingPlaceFormat2Choice",
					"type": "object",
					"additionalProperties": false
				},
				"Balance": {
					"$ref": "#/definitions/CorporateActionBalanceDetails22",
					"type": "object",
					"additionalProperties": false
				}
			},
			"required": ["SafekeepingAccount","Balance"],
			"type": "object"
		},
		"PartyIdentification36Choice": {
			"oneOf":[
				{"required":["AnyBIC"]},
				{"required":["ProprietaryIdentification"]}
			],
			"properties":{
				"AnyBIC": {
					"$ref": "#/definitions/AnyBICIdentifier",
					"type": "string"
				},
				"ProprietaryIdentification": {
					"$ref": "#/definitions/GenericIdentification19",
					"type": "object",
					"additionalProperties": false
				}},
			"additionalProperties": false,
			"type": "object"
		},
		"AnyBICIdentifier" : {
		
			"pattern":"^[A-Z]{6,6}[A-Z2-9][A-NP-Z0-9]([A-Z0-9]{3,3}){0,1}$",
			"type":"string"
		},
		"SafekeepingPlaceFormat2Choice": {
			"oneOf":[
				{"required":["Identification"]},
				{"required":["Country"]},
				{"required":["TypeAndIdentification"]},
				{"required":["Proprietary"]}
			],
			"properties":{
				"Identification": {
					"$ref": "#/definitions/SafekeepingPlaceTypeAndText2",
					"type": "object",
					"additionalProperties": false
				},
				"Country": {
					"$ref": "#/definitions/CountryCode",
					"type": "string"
				},
				"TypeAndIdentification": {
					"$ref": "#/definitions/SafekeepingPlaceTypeAndAnyBICIdentifier1",
					"type": "object",
					"additionalProperties": false
				},
				"Proprietary": {
					"$ref": "#/definitions/GenericIdentification21",
					"type": "object",
					"additionalProperties": false
				}},
			"additionalProperties": false,
			"type": "object"
		},
		"SafekeepingPlaceTypeAndText2": {
			"additionalProperties": false,
			"properties": {
				"SafekeepingPlaceType": {
					"$ref": "#/definitions/SafekeepingPlace2Code",
					"type": "string"
				},
				"Identification": {
					"$ref": "#/definitions/Max35Text",
					"type": "string"
				}
			},
			"required": ["SafekeepingPlaceType"],
			"type": "object"
		},
		"SafekeepingPlace2Code": {
			"enum":["SHHE","ALLP"],			
			"type": "string"
		},
		"CountryCode": {
			"pattern": "^[A-Z]{2,2}$",			
			"type": "string"
		},
		"SafekeepingPlaceTypeAndAnyBICIdentifier1": {
			"additionalProperties": false,
			"properties": {
				"SafekeepingPlaceType": {
					"$ref": "#/definitions/SafekeepingPlace1Code",
					"type": "string"
				},
				"Identification": {
					"$ref": "#/definitions/AnyBICIdentifier",
					"type": "string"
				}
			},
			"required": ["SafekeepingPlaceType","Identification"],
			"type": "object"
		},
		"SafekeepingPlace1Code": {
			"enum":["CUST","ICSD","NCSD","SHHE"],			
			"type": "string"
		},
		"GenericIdentification21": {
			"additionalProperties": false,
			"properties": {
				"Type": {
					"$ref": "#/definitions/GenericIdentification20",
					"type": "object",
					"additionalProperties": false
				},
				"Identification": {
					"$ref": "#/definitions/Max35Text",
					"type": "string"
				}
			},
			"required": ["Type"],
			"type": "object"
		},
		"CorporateActionBalanceDetails22": {
			"additionalProperties": false,
			"properties": {
				"ConfirmedBalance": {
					"$ref": "#/definitions/BalanceFormat1Choice",
					"type": "object",
					"additionalProperties": false
				},
				"TotalEligibleBalance": {
					"$ref": "#/definitions/TotalEligibleBalanceFormat1",
					"type": "object",
					"additionalProperties": false
				},
				"BlockedBalance": {
					"$ref": "#/definitions/BalanceFormat1Choice",
					"type": "object",
					"additionalProperties": false
				},
				"BorrowedBalance": {
					"$ref": "#/definitions/BalanceFormat1Choice",
					"type": "object",
					"additionalProperties": false
				},
				"CollateralInBalance": {
					"$ref": "#/definitions/BalanceFormat1Choice",
					"type": "object",
					"additionalProperties": false
				},
				"CollateralOutBalance": {
					"$ref": "#/definitions/BalanceFormat1Choice",
					"type": "object",
					"additionalProperties": false
				},
				"OnLoanBalance": {
					"$ref": "#/definitions/BalanceFormat1Choice",
					"type": "object",
					"additionalProperties": false
				},
				"PendingDeliveryBalance": {
					"items": {
						"$ref": "#/definitions/BalanceFormat3Choice"
					},
					"type": "array"
				},
				"PendingReceiptBalance": {
					"items": {
						"$ref": "#/definitions/BalanceFormat3Choice"
					},
					"type": "array"
				},
				"OutForRegistrationBalance": {
					"$ref": "#/definitions/BalanceFormat1Choice",
					"type": "object",
					"additionalProperties": false
				},
				"SettlementPositionBalance": {
					"items": {
						"$ref": "#/definitions/BalanceFormat3Choice"
					},
					"type": "array"
				},
				"StreetPositionBalance": {
					"$ref": "#/definitions/BalanceFormat1Choice",
					"type": "object",
					"additionalProperties": false
				},
				"TradeDatePositionBalance": {
					"$ref": "#/definitions/BalanceFormat1Choice",
					"type": "object",
					"additionalProperties": false
				},
				"InTransshipmentBalance": {
					"$ref": "#/definitions/BalanceFormat1Choice",
					"type": "object",
					"additionalProperties": false
				},
				"RegisteredBalance": {
					"$ref": "#/definitions/BalanceFormat1Choice",
					"type": "object",
					"additionalProperties": false
				},
				"AffectedBalance": {
					"$ref": "#/definitions/BalanceFormat1Choice",
					"type": "object",
					"additionalProperties": false
				},
				"UnaffectedBalance": {
					"$ref": "#/definitions/BalanceFormat1Choice",
					"type": "object",
					"additionalProperties": false
				}
			},
			"required": ["ConfirmedBalance"],
			"type": "object"
		},
		"BalanceFormat1Choice": {
			"oneOf":[
				{"required":["Balance"]},
				{"required":["EligibleBalance"]},
				{"required":["NotEligibleBalance"]}
			],
			"properties":{
				"Balance": {
					"$ref": "#/definitions/SignedQuantityFormat1",
					"type": "object",
					"additionalProperties": false
				},
				"EligibleBalance": {
					"$ref": "#/definitions/SignedQuantityFormat2",
					"type": "object",
					"additionalProperties": false
				},
				"NotEligibleBalance": {
					"$ref": "#/definitions/SignedQuantityFormat2",
					"type": "object",
					"additionalProperties": false
				}},
			"additionalProperties": false,
			"type": "object"
		},
		"SignedQuantityFormat1": {
			"additionalProperties": false,
			"properties": {
				"ShortLongPosition": {
					"$ref": "#/definitions/ShortLong1Code",
					"type": "string"
				},
				"QuantityChoice": {
					"$ref": "#/definitions/Quantity2Choice",
					"type": "object",
					"additionalProperties": false
				}
			},
			"required": ["ShortLongPosition","QuantityChoice"],
			"type": "object"
		},
		"ShortLong1Code": {
			"enum":["SHOR","LONG"],			
			"type": "string"
		},
		"Quantity2Choice": {
			"oneOf":[
				{"required":["Quantity"]},
				{"required":["ProprietaryQuantity"]}
			],
			"properties":{
				"Quantity": {
					"$ref": "#/definitions/FinancialInstrumentQuantity1Choice",
					"type": "object",
					"additionalProperties": false
				},
				"ProprietaryQuantity": {
					"$ref": "#/definitions/ProprietaryQuantity2",
					"type": "object",
					"additionalProperties": false
				}},
			"additionalProperties": false,
			"type": "object"
		},
		"ProprietaryQuantity2": {
			"additionalProperties": false,
			"properties": {
				"Quantity": {
					"$ref": "#/definitions/DecimalNumber",
					"type": "string"
				},
				"QuantityType": {
					"$ref": "#/definitions/Exact4AlphaNumericText",
					"type": "string"
				},
				"Issuer": {
					"$ref": "#/definitions/Max35Text",
					"type": "string"
				},
				"SchemeName": {
					"$ref": "#/definitions/Max35Text",
					"type": "string"
				}
			},
			"required": ["Quantity","QuantityType","Issuer"],
			"type": "object"
		},
		"SignedQuantityFormat2": {
			"additionalProperties": false,
			"properties": {
				"ShortLongPosition": {
					"$ref": "#/definitions/ShortLong1Code",
					"type": "string"
				},
				"Quantity": {
					"$ref": "#/definitions/FinancialInstrumentQuantity1Choice",
					"type": "object",
					"additionalProperties": false
				}
			},
			"required": ["ShortLongPosition","Quantity"],
			"type": "object"
		},
		"TotalEligibleBalanceFormat1": {
			"additionalProperties": false,
			"properties": {
				"Balance": {
					"$ref": "#/definitions/Quantity3Choice",
					"type": "object",
					"additionalProperties": false
				},
				"FullPeriodUnits": {
					"$ref": "#/definitions/SignedQuantityFormat2",
					"type": "object",
					"additionalProperties": false
				},
				"PartWayPeriodUnits": {
					"$ref": "#/definitions/SignedQuantityFormat2",
					"type": "object",
					"additionalProperties": false
				}
			},
			"type": "object"
		},
		"Quantity3Choice": {
			"oneOf":[
				{"required":["QuantityChoice"]},
				{"required":["ProprietaryQuantity"]}
			],
			"properties":{
				"QuantityChoice": {
					"$ref": "#/definitions/Quantity4Choice",
					"type": "object",
					"additionalProperties": false
				},
				"ProprietaryQuantity": {
					"$ref": "#/definitions/ProprietaryQuantity3",
					"type": "object",
					"additionalProperties": false
				}},
			"additionalProperties": false,
			"type": "object"
		},
		"Quantity4Choice": {
			"oneOf":[
				{"required":["OriginalAndCurrentFaceAmount"]},
				{"required":["SignedQuantity"]}
			],
			"properties":{
				"OriginalAndCurrentFaceAmount": {
					"$ref": "#/definitions/OriginalAndCurrentQuantities2",
					"type": "object",
					"additionalProperties": false
				},
				"SignedQuantity": {
					"$ref": "#/definitions/SignedQuantityFormat2",
					"type": "object",
					"additionalProperties": false
				}},
			"additionalProperties": false,
			"type": "object"
		},
		"OriginalAndCurrentQuantities2": {
			"additionalProperties": false,
			"properties": {
				"ShortLongPosition": {
					"$ref": "#/definitions/ShortLong1Code",
					"type": "string"
				},
				"FaceAmount": {
					"$ref": "#/definitions/ImpliedCurrencyAndAmount",
					"type": "string"
				},
				"AmortisedValue": {
					"$ref": "#/definitions/ImpliedCurrencyAndAmount",
					"type": "string"
				}
			},
			"required": ["ShortLongPosition","FaceAmount","AmortisedValue"],
			"type": "object"
		},
		"ProprietaryQuantity3": {
			"additionalProperties": false,
			"properties": {
				"ShortLongPosition": {
					"$ref": "#/definitions/ShortLong1Code",
					"type": "string"
				},
				"Quantity": {
					"$ref": "#/definitions/DecimalNumber",
					"type": "string"
				},
				"QuantityType": {
					"$ref": "#/definitions/Exact4AlphaNumericText",
					"type": "string"
				},
				"Issuer": {
					"$ref": "#/definitions/Max35Text",
					"type": "string"
				},
				"SchemeName": {
					"$ref": "#/definitions/Max35Text",
					"type": "string"
				}
			},
			"required": ["Quantity","QuantityType","Issuer"],
			"type": "object"
		},
		"BalanceFormat3Choice": {
			"oneOf":[
				{"required":["Balance"]},
				{"required":["EligibleBalance"]},
				{"required":["NotEligibleBalance"]},
				{"required":["FullPeriodUnits"]},
				{"required":["PartWayPeriodUnits"]}
			],
			"properties":{
				"Balance": {
					"$ref": "#/definitions/SignedQuantityFormat1",
					"type": "object",
					"additionalProperties": false
				},
				"EligibleBalance": {
					"$ref": "#/definitions/SignedQuantityFormat2",
					"type": "object",
					"additionalProperties": false
				},
				"NotEligibleBalance": {
					"$ref": "#/definitions/SignedQuantityFormat2",
					"type": "object",
					"additionalProperties": false
				},
				"FullPeriodUnits": {
					"$ref": "#/definitions/SignedQuantityFormat2",
					"type": "object",
					"additionalProperties": false
				},
				"PartWayPeriodUnits": {
					"$ref": "#/definitions/SignedQuantityFormat2",
					"type": "object",
					"additionalProperties": false
				}},
			"additionalProperties": false,
			"type": "object"
		},
		"CorporateAction14": {
			"additionalProperties": false,
			"properties": {
				"DateDetails": {
					"$ref": "#/definitions/CorporateActionDate30",
					"type": "object",
					"additionalProperties": false
				},
				"LotteryType": {
					"$ref": "#/definitions/LotteryTypeFormat1Choice",
					"type": "object",
					"additionalProperties": false
				}
			},
			"type": "object"
		},
		"CorporateActionDate30": {
			"additionalProperties": false,
			"properties": {
				"RecordDate": {
					"$ref": "#/definitions/DateFormat19Choice",
					"type": "object",
					"additionalProperties": false
				},
				"ExDividendDate": {
					"$ref": "#/definitions/DateFormat19Choice",
					"type": "object",
					"additionalProperties": false
				}
			},
			"type": "object"
		},
		"DateFormat19Choice": {
			"oneOf":[
				{"required":["Date"]},
				{"required":["DateCode"]}
			],
			"properties":{
				"Date": {
					"$ref": "#/definitions/DateAndDateTimeChoice",
					"type": "object",
					"additionalProperties": false
				},
				"DateCode": {
					"$ref": "#/definitions/DateCode11Choice",
					"type": "object",
					"additionalProperties": false
				}},
			"additionalProperties": false,
			"type": "object"
		},
		"DateAndDateTimeChoice": {
			"oneOf":[
				{"required":["Date"]},
				{"required":["DateTime"]}
			],
			"properties":{
				"Date": {
					"$ref": "#/definitions/ISODate",
					"type": "string"
				},
				"DateTime": {
					"$ref": "#/definitions/ISODateTime",
					"type": "string"
				}},
			"additionalProperties": false,
			"type": "object"
		},
		"ISODate" : {
		
			"type":"string"
		},
		"ISODateTime" : {
		
			"type":"string"
		},
		"DateCode11Choice": {
			"oneOf":[
				{"required":["Code"]},
				{"required":["Proprietary"]}
			],
			"properties":{
				"Code": {
					"$ref": "#/definitions/DateType8Code",
					"type": "string"
				},
				"Proprietary": {
					"$ref": "#/definitions/GenericIdentification20",
					"type": "object",
					"additionalProperties": false
				}},
			"additionalProperties": false,
			"type": "object"
		},
		"DateType8Code": {
			"enum":["UKWN","ONGO"],			
			"type": "string"
		},
		"LotteryTypeFormat1Choice": {
			"oneOf":[
				{"required":["Code"]},
				{"required":["Proprietary"]}
			],
			"properties":{
				"Code": {
					"$ref": "#/definitions/LotteryType1Code",
					"type": "string"
				},
				"Proprietary": {
					"$ref": "#/definitions/GenericIdentification20",
					"type": "object",
					"additionalProperties": false
				}},
			"additionalProperties": false,
			"type": "object"
		},
		"LotteryType1Code": {
			"enum":["ORIG","SUPP"],			
			"type": "string"
		},
		"CorporateActionOption102": {
			"additionalProperties": false,
			"properties": {
				"OptionNumber": {
					"$ref": "#/definitions/OptionNumber1Choice",
					"type": "object",
					"additionalProperties": false
				},
				"OptionType": {
					"$ref": "#/definitions/CorporateActionOption11Choice",
					"type": "object",
					"additionalProperties": false
				},
				"OptionFeatures": {
					"items": {
						"$ref": "#/definitions/OptionFeaturesFormat1Choice"
					},
					"type": "array"
				},
				"FractionDisposition": {
					"$ref": "#/definitions/FractionDispositionType23Choice",
					"type": "object",
					"additionalProperties": false
				},
				"CurrencyOption": {
					"$ref": "#/definitions/ActiveCurrencyCode",
					"type": "string"
				},
				"DateDetails": {
					"$ref": "#/definitions/CorporateActionDate18",
					"type": "object",
					"additionalProperties": false
				},
				"PeriodDetails": {
					"$ref": "#/definitions/CorporateActionPeriod9",
					"type": "object",
					"additionalProperties": false
				},
				"RateAndAmountDetails": {
					"$ref": "#/definitions/CorporateActionRate46",
					"type": "object",
					"additionalProperties": false
				},
				"PriceDetails": {
					"$ref": "#/definitions/CorporateActionPrice30",
					"type": "object",
					"additionalProperties": false
				},
				"PlaceOfTrade": {
					"$ref": "#/definitions/MarketIdentification78",
					"type": "object",
					"additionalProperties": false
				},
				"SecuritiesMovementDetails": {
					"items": {
						"$ref": "#/definitions/SecuritiesOption42"
					},
					"type": "array"
				},
				"CashMovementDetails": {
					"items": {
						"$ref": "#/definitions/CashOption30"
					},
					"type": "array"
				}
			},
			"required": ["OptionNumber","OptionType"],
			"type": "object"
		},
		"OptionNumber1Choice": {
			"oneOf":[
				{"required":["Number"]},
				{"required":["Code"]}
			],
			"properties":{
				"Number": {
					"$ref": "#/definitions/Exact3NumericText",
					"type": "string"
				},
				"Code": {
					"$ref": "#/definitions/OptionNumber1Code",
					"type": "string"
				}},
			"additionalProperties": false,
			"type": "object"
		},
		"OptionNumber1Code": {
			"enum":["UNSO"],			
			"type": "string"
		},
		"CorporateActionOption11Choice": {
			"oneOf":[
				{"required":["Code"]},
				{"required":["Proprietary"]}
			],
			"properties":{
				"Code": {
					"$ref": "#/definitions/CorporateActionOption8Code",
					"type": "string"
				},
				"Proprietary": {
					"$ref": "#/definitions/GenericIdentification20",
					"type": "object",
					"additionalProperties": false
				}},
			"additionalProperties": false,
			"type": "object"
		},
		"CorporateActionOption8Code": {
			"enum":["ABST","BSPL","BUYA","CEXC","CTEN","CONN","CONY","EXER","LAPS","MKDW","MKUP","NOQU","OTHR","OVER","OFFR","PROX","QINV","MPUT","SLLE","SPLI","AMGT","MNGT","SECU","CASH","CASE","NOAC","PRUN"],			
			"type": "string"
		},
		"OptionFeaturesFormat1Choice": {
			"oneOf":[
				{"required":["Code"]},
				{"required":["Proprietary"]}
			],
			"properties":{
				"Code": {
					"$ref": "#/definitions/OptionFeatures1Code",
					"type": "string"
				},
				"Proprietary": {
					"$ref": "#/definitions/GenericIdentification20",
					"type": "object",
					"additionalProperties": false
				}},
			"additionalProperties": false,
			"type": "object"
		},
		"OptionFeatures1Code": {
			"enum":["COND","MAXC","MAXS","OPLF","PROR","QOVE","QREC","VVPR"],			
			"type": "string"
		},
		"FractionDispositionType23Choice": {
			"oneOf":[
				{"required":["Code"]},
				{"required":["Proprietary"]}
			],
			"properties":{
				"Code": {
					"$ref": "#/definitions/FractionDispositionType11Code",
					"type": "string"
				},
				"Proprietary": {
					"$ref": "#/definitions/GenericIdentification20",
					"type": "object",
					"additionalProperties": false
				}},
			"additionalProperties": false,
			"type": "object"
		},
		"FractionDispositionType11Code": {
			"enum":["BUYU","CINL","RDUP","RDDN","STAN","DIST"],			
			"type": "string"
		},
		"ActiveCurrencyCode": {
			"pattern": "^[A-Z]{3,3}$",			
			"type": "string"
		},
		"CorporateActionDate18": {
			"additionalProperties": false,
			"properties": {
				"ResponseDeadline": {
					"$ref": "#/definitions/DateFormat19Choice",
					"type": "object",
					"additionalProperties": false
				},
				"SubscriptionCostDebitDate": {
					"$ref": "#/definitions/DateFormat19Choice",
					"type": "object",
					"additionalProperties": false
				},
				"MarketDeadline": {
					"$ref": "#/definitions/DateFormat19Choice",
					"type": "object",
					"additionalProperties": false
				},
				"ExpiryDate": {
					"$ref": "#/definitions/DateFormat19Choice",
					"type": "object",
					"additionalProperties": false
				},
				"CoverExpirationDate": {
					"$ref": "#/definitions/DateFormat19Choice",
					"type": "object",
					"additionalProperties": false
				},
				"ProtectDate": {
					"$ref": "#/definitions/DateFormat19Choice",
					"type": "object",
					"additionalProperties": false
				},
				"TradingDate": {
					"$ref": "#/definitions/DateFormat19Choice",
					"type": "object",
					"additionalProperties": false
				}
			},
			"type": "object"
		},
		"CorporateActionPeriod9": {
			"additionalProperties": false,
			"properties": {
				"PriceCalculationPeriod": {
					"$ref": "#/definitions/Period5",
					"type": "object",
					"additionalProperties": false
				},
				"ActionPeriod": {
					"$ref": "#/definitions/Period5",
					"type": "object",
					"additionalProperties": false
				},
				"ParallelTradingPeriod": {
					"$ref": "#/definitions/Period5",
					"type": "object",
					"additionalProperties": false
				}
			},
			"type": "object"
		},
		"Period5": {
			"additionalProperties": false,
			"properties": {
				"StartDate": {
					"$ref": "#/definitions/DateFormat21Choice",
					"type": "object",
					"additionalProperties": false
				},
				"EndDate": {
					"$ref": "#/definitions/DateFormat21Choice",
					"type": "object",
					"additionalProperties": false
				}
			},
			"required": ["StartDate","EndDate"],
			"type": "object"
		},
		"DateFormat21Choice": {
			"oneOf":[
				{"required":["Date"]},
				{"required":["NotSpecifiedDate"]}
			],
			"properties":{
				"Date": {
					"$ref": "#/definitions/DateAndDateTimeChoice",
					"type": "object",
					"additionalProperties": false
				},
				"NotSpecifiedDate": {
					"$ref": "#/definitions/DateType8Code",
					"type": "string"
				}},
			"additionalProperties": false,
			"type": "object"
		},
		"CorporateActionRate46": {
			"additionalProperties": false,
			"properties": {
				"GrossDividendRate": {
					"items": {
						"$ref": "#/definitions/GrossDividendRateFormat10Choice"
					},
					"type": "array"
				},
				"NetDividendRate": {
					"items": {
						"$ref": "#/definitions/NetDividendRateFormat12Choice"
					},
					"type": "array"
				},
				"IndexFactor": {
					"$ref": "#/definitions/RateAndAmountFormat5Choice",
					"type": "object",
					"additionalProperties": false
				},
				"InterestRateUsedForPayment": {
					"items": {
						"$ref": "#/definitions/InterestRateUsedForPaymentFormat2Choice"
					},
					"type": "array"
				},
				"MaximumAllowedOversubscriptionRate": {
					"$ref": "#/definitions/PercentageRate",
					"type": "string"
				},
				"ProrationRate": {
					"$ref": "#/definitions/PercentageRate",
					"type": "string"
				},
				"TaxRelatedRate": {
					"items": {
						"$ref": "#/definitions/RateTypeAndAmountAndStatus6"
					},
					"type": "array"
				},
				"WithholdingTaxRate": {
					"items": {
						"$ref": "#/definitions/RateFormat11Choice"
					},
					"type": "array"
				},
				"AdditionalTax": {
					"$ref": "#/definitions/RateAndAmountFormat5Choice",
					"type": "object",
					"additionalProperties": false
				},
				"WithholdingOfForeignTax": {
					"items": {
						"$ref": "#/definitions/RateAndAmountFormat21Choice"
					},
					"type": "array"
				},
				"TaxableIncomePerDividendShare": {
					"items": {
						"$ref": "#/definitions/RateTypeAndAmountAndStatus11"
					},
					"type": "array"
				}
			},
			"type": "object"
		},
		"GrossDividendRateFormat10Choice": {
			"oneOf":[
				{"required":["Amount"]},
				{"required":["RateTypeAndAmountAndRateStatus"]}
			],
			"properties":{
				"Amount": {
					"$ref": "#/definitions/ActiveCurrencyAnd13DecimalAmount",
					"type": "string"
				},
				"RateTypeAndAmountAndRateStatus": {
					"$ref": "#/definitions/RateTypeAndAmountAndStatus15",
					"type": "object",
					"additionalProperties": false
				}},
			"additionalProperties": false,
			"type": "object"
		},
		"ActiveCurrencyAnd13DecimalAmount" : {
			"type":"object",
			"properties":{
				"$": {
					"maxLength":18,
					"type":"string" 
				},
				"ActiveCurrencyCode":{
					"$ref":"#/definitions/ActiveCurrencyCode"
				}
			}
			
		},
		"RateTypeAndAmountAndStatus15": {
			"additionalProperties": false,
			"properties": {
				"RateType": {
					"$ref": "#/definitions/RateType22Choice",
					"type": "object",
					"additionalProperties": false
				},
				"Amount": {
					"$ref": "#/definitions/ActiveCurrencyAnd13DecimalAmount",
					"type": "string"
				},
				"RateStatus": {
					"$ref": "#/definitions/RateStatus1Choice",
					"type": "object",
					"additionalProperties": false
				}
			},
			"required": ["RateType","Amount"],
			"type": "object"
		},
		"RateType22Choice": {
			"oneOf":[
				{"required":["Code"]},
				{"required":["Proprietary"]}
			],
			"properties":{
				"Code": {
					"$ref": "#/definitions/GrossDividendRateType3Code",
					"type": "string"
				},
				"Proprietary": {
					"$ref": "#/definitions/GenericIdentification20",
					"type": "object",
					"additionalProperties": false
				}},
			"additionalProperties": false,
			"type": "object"
		},
		"GrossDividendRateType3Code": {
			"enum":["CAPO","FLFR","INCO","INTR","SOIC","TXBL","TXDF","TXFR","UNFR","LTCG","STCG","REES"],			
			"type": "string"
		},
		"RateStatus1Choice": {
			"oneOf":[
				{"required":["Code"]},
				{"required":["Proprietary"]}
			],
			"properties":{
				"Code": {
					"$ref": "#/definitions/RateStatus1Code",
					"type": "string"
				},
				"Proprietary": {
					"$ref": "#/definitions/GenericIdentification20",
					"type": "object",
					"additionalProperties": false
				}},
			"additionalProperties": false,
			"type": "object"
		},
		"RateStatus1Code": {
			"enum":["ACTU","INDI"],			
			"type": "string"
		},
		"NetDividendRateFormat12Choice": {
			"oneOf":[
				{"required":["Amount"]},
				{"required":["RateTypeAndAmountAndRateStatus"]}
			],
			"properties":{
				"Amount": {
					"$ref": "#/definitions/ActiveCurrencyAnd13DecimalAmount",
					"type": "string"
				},
				"RateTypeAndAmountAndRateStatus": {
					"$ref": "#/definitions/RateTypeAndAmountAndStatus16",
					"type": "object",
					"additionalProperties": false
				}},
			"additionalProperties": false,
			"type": "object"
		},
		"RateTypeAndAmountAndStatus16": {
			"additionalProperties": false,
			"properties": {
				"RateType": {
					"$ref": "#/definitions/RateType23Choice",
					"type": "object",
					"additionalProperties": false
				},
				"Amount": {
					"$ref": "#/definitions/ActiveCurrencyAnd13DecimalAmount",
					"type": "string"
				},
				"RateStatus": {
					"$ref": "#/definitions/RateStatus1Choice",
					"type": "object",
					"additionalProperties": false
				}
			},
			"required": ["RateType","Amount"],
			"type": "object"
		},
		"RateType23Choice": {
			"oneOf":[
				{"required":["Code"]},
				{"required":["Proprietary"]}
			],
			"properties":{
				"Code": {
					"$ref": "#/definitions/NetDividendRateType3Code",
					"type": "string"
				},
				"Proprietary": {
					"$ref": "#/definitions/GenericIdentification20",
					"type": "object",
					"additionalProperties": false
				}},
			"additionalProperties": false,
			"type": "object"
		},
		"NetDividendRateType3Code": {
			"enum":["CAPO","FLFR","INCO","INTR","SOIC","TXBL","TXDF","TXFR","UNFR","REES"],			
			"type": "string"
		},
		"RateAndAmountFormat5Choice": {
			"oneOf":[
				{"required":["Rate"]},
				{"required":["Amount"]}
			],
			"properties":{
				"Rate": {
					"$ref": "#/definitions/PercentageRate",
					"type": "string"
				},
				"Amount": {
					"$ref": "#/definitions/ActiveCurrencyAnd13DecimalAmount",
					"type": "string"
				}},
			"additionalProperties": false,
			"type": "object"
		},
		"PercentageRate" : {
		
			"maxLength":11,
			"type":"string"
		},
		"InterestRateUsedForPaymentFormat2Choice": {
			"oneOf":[
				{"required":["Rate"]},
				{"required":["Amount"]},
				{"required":["RateTypeAndAmountAndRateStatus"]}
			],
			"properties":{
				"Rate": {
					"$ref": "#/definitions/PercentageRate",
					"type": "string"
				},
				"Amount": {
					"$ref": "#/definitions/ActiveCurrencyAnd13DecimalAmount",
					"type": "string"
				},
				"RateTypeAndAmountAndRateStatus": {
					"$ref": "#/definitions/RateTypeAndAmountAndStatus3",
					"type": "object",
					"additionalProperties": false
				}},
			"additionalProperties": false,
			"type": "object"
		},
		"RateTypeAndAmountAndStatus3": {
			"additionalProperties": false,
			"properties": {
				"RateType": {
					"$ref": "#/definitions/RateType6Choice",
					"type": "object",
					"additionalProperties": false
				},
				"Amount": {
					"$ref": "#/definitions/ActiveCurrencyAnd13DecimalAmount",
					"type": "string"
				},
				"RateStatus": {
					"$ref": "#/definitions/RateStatus1Choice",
					"type": "object",
					"additionalProperties": false
				}
			},
			"required": ["RateType","Amount"],
			"type": "object"
		},
		"RateType6Choice": {
			"oneOf":[
				{"required":["Code"]},
				{"required":["Proprietary"]}
			],
			"properties":{
				"Code": {
					"$ref": "#/definitions/RateType7Code",
					"type": "string"
				},
				"Proprietary": {
					"$ref": "#/definitions/GenericIdentification20",
					"type": "object",
					"additionalProperties": false
				}},
			"additionalProperties": false,
			"type": "object"
		},
		"RateType7Code": {
			"enum":["SCHD","USCD"],			
			"type": "string"
		},
		"RateTypeAndAmountAndStatus6": {
			"additionalProperties": false,
			"properties": {
				"RateType": {
					"$ref": "#/definitions/RateType11Choice",
					"type": "object",
					"additionalProperties": false
				},
				"Amount": {
					"$ref": "#/definitions/ActiveCurrencyAnd13DecimalAmount",
					"type": "string"
				},
				"RateStatus": {
					"$ref": "#/definitions/RateStatus1Choice",
					"type": "object",
					"additionalProperties": false
				}
			},
			"required": ["RateType","Amount"],
			"type": "object"
		},
		"RateType11Choice": {
			"oneOf":[
				{"required":["Code"]},
				{"required":["Proprietary"]}
			],
			"properties":{
				"Code": {
					"$ref": "#/definitions/TaxType4Code",
					"type": "string"
				},
				"Proprietary": {
					"$ref": "#/definitions/GenericIdentification20",
					"type": "object",
					"additionalProperties": false
				}},
			"additionalProperties": false,
			"type": "object"
		},
		"TaxType4Code": {
			"enum":["WITF","WITL"],			
			"type": "string"
		},
		"RateFormat11Choice": {
			"oneOf":[
				{"required":["Rate"]},
				{"required":["RateTypeAndRate"]}
			],
			"properties":{
				"Rate": {
					"$ref": "#/definitions/PercentageRate",
					"type": "string"
				},
				"RateTypeAndRate": {
					"$ref": "#/definitions/RateTypeAndPercentageRate1",
					"type": "object",
					"additionalProperties": false
				}},
			"additionalProperties": false,
			"type": "object"
		},
		"RateTypeAndPercentageRate1": {
			"additionalProperties": false,
			"properties": {
				"RateType": {
					"$ref": "#/definitions/RateType28Choice",
					"type": "object",
					"additionalProperties": false
				},
				"Rate": {
					"$ref": "#/definitions/PercentageRate",
					"type": "string"
				}
			},
			"required": ["RateType","Rate"],
			"type": "object"
		},
		"RateType28Choice": {
			"oneOf":[
				{"required":["Code"]},
				{"required":["Proprietary"]}
			],
			"properties":{
				"Code": {
					"$ref": "#/definitions/WithholdingTaxRateType1Code",
					"type": "string"
				},
				"Proprietary": {
					"$ref": "#/definitions/GenericIdentification20",
					"type": "object",
					"additionalProperties": false
				}},
			"additionalProperties": false,
			"type": "object"
		},
		"WithholdingTaxRateType1Code": {
			"enum":["FTCA","NRAT","BWIT"],			
			"type": "string"
		},
		"RateAndAmountFormat21Choice": {
			"oneOf":[
				{"required":["Rate"]},
				{"required":["Amount"]},
				{"required":["RateTypeAndRate"]}
			],
			"properties":{
				"Rate": {
					"$ref": "#/definitions/PercentageRate",
					"type": "string"
				},
				"Amount": {
					"$ref": "#/definitions/ActiveCurrencyAnd13DecimalAmount",
					"type": "string"
				},
				"RateTypeAndRate": {
					"$ref": "#/definitions/RateTypeAndPercentageRate1",
					"type": "object",
					"additionalProperties": false
				}},
			"additionalProperties": false,
			"type": "object"
		},
		"RateTypeAndAmountAndStatus11": {
			"additionalProperties": false,
			"properties": {
				"RateType": {
					"$ref": "#/definitions/RateType17Choice",
					"type": "object",
					"additionalProperties": false
				},
				"Amount": {
					"$ref": "#/definitions/ActiveCurrencyAnd13DecimalAmount",
					"type": "string"
				},
				"RateStatus": {
					"$ref": "#/definitions/RateStatus1Choice",
					"type": "object",
					"additionalProperties": false
				}
			},
			"required": ["RateType","Amount"],
			"type": "object"
		},
		"RateType17Choice": {
			"oneOf":[
				{"required":["Code"]},
				{"required":["Proprietary"]}
			],
			"properties":{
				"Code": {
					"$ref": "#/definitions/DividendRateType1Code",
					"type": "string"
				},
				"Proprietary": {
					"$ref": "#/definitions/GenericIdentification20",
					"type": "object",
					"additionalProperties": false
				}},
			"additionalProperties": false,
			"type": "object"
		},
		"DividendRateType1Code": {
			"enum":["TXBL"],			
			"type": "string"
		},
		"CorporateActionPrice30": {
			"additionalProperties": false,
			"properties": {
				"CashInLieuOfSharePrice": {
					"$ref": "#/definitions/PriceFormat5Choice",
					"type": "object",
					"additionalProperties": false
				},
				"OverSubscriptionDepositPrice": {
					"$ref": "#/definitions/PriceFormat5Choice",
					"type": "object",
					"additionalProperties": false
				}
			},
			"type": "object"
		},
		"PriceFormat5Choice": {
			"oneOf":[
				{"required":["PercentagePrice"]},
				{"required":["AmountPrice"]}
			],
			"properties":{
				"PercentagePrice": {
					"$ref": "#/definitions/PercentagePrice1",
					"type": "object",
					"additionalProperties": false
				},
				"AmountPrice": {
					"$ref": "#/definitions/AmountPrice3",
					"type": "object",
					"additionalProperties": false
				}},
			"additionalProperties": false,
			"type": "object"
		},
		"PercentagePrice1": {
			"additionalProperties": false,
			"properties": {
				"PercentagePriceType": {
					"$ref": "#/definitions/PriceRateType3Code",
					"type": "string"
				},
				"PriceValue": {
					"$ref": "#/definitions/PercentageRate",
					"type": "string"
				}
			},
			"required": ["PercentagePriceType","PriceValue"],
			"type": "object"
		},
		"PriceRateType3Code": {
			"enum":["DISC","PREM","YIEL","PRCT"],			
			"type": "string"
		},
		"AmountPrice3": {
			"additionalProperties": false,
			"properties": {
				"AmountPriceType": {
					"$ref": "#/definitions/AmountPriceType1Code",
					"type": "string"
				},
				"PriceValue": {
					"$ref": "#/definitions/ActiveCurrencyAnd13DecimalAmount",
					"type": "string"
				}
			},
			"required": ["AmountPriceType","PriceValue"],
			"type": "object"
		},
		"AmountPriceType1Code": {
			"enum":["ACTU","DISC","PLOT","PREM"],			
			"type": "string"
		},
		"MarketIdentification78": {
			"additionalProperties": false,
			"properties": {
				"Identification": {
					"$ref": "#/definitions/MarketIdentification1Choice",
					"type": "object",
					"additionalProperties": false
				},
				"Type": {
					"$ref": "#/definitions/MarketType3Choice",
					"type": "object",
					"additionalProperties": false
				}
			},
			"required": ["Type"],
			"type": "object"
		},
		"MarketIdentification1Choice": {
			"oneOf":[
				{"required":["MarketIdentifierCode"]},
				{"required":["Description"]}
			],
			"properties":{
				"MarketIdentifierCode": {
					"$ref": "#/definitions/MICIdentifier",
					"type": "string"
				},
				"Description": {
					"$ref": "#/definitions/Max35Text",
					"type": "string"
				}},
			"additionalProperties": false,
			"type": "object"
		},
		"MICIdentifier" : {
		
			"pattern":"^[A-Z0-9]{4,4}$",
			"type":"string"
		},
		"MarketType3Choice": {
			"oneOf":[
				{"required":["Code"]},
				{"required":["Proprietary"]}
			],
			"properties":{
				"Code": {
					"$ref": "#/definitions/MarketType2Code",
					"type": "string"
				},
				"Proprietary": {
					"$ref": "#/definitions/GenericIdentification20",
					"type": "object",
					"additionalProperties": false
				}},
			"additionalProperties": false,
			"type": "object"
		},
		"MarketType2Code": {
			"enum":["PRIM","SECM","OTCO","VARI","EXCH"],			
			"type": "string"
		},
		"SecuritiesOption42": {
			"additionalProperties": false,
			"properties": {
				"FinancialInstrumentIdentification": {
					"$ref": "#/definitions/SecurityIdentification14",
					"type": "object",
					"additionalProperties": false
				},
				"CreditDebitIndicator": {
					"$ref": "#/definitions/CreditDebitCode",
					"type": "string"
				},
				"TemporaryFinancialInstrumentIndicator": {
					"$ref": "#/definitions/TemporaryFinancialInstrumentIndicator1Choice",
					"type": "object",
					"additionalProperties": false
				},
				"NewSecuritiesIssuanceIndicator": {
					"$ref": "#/definitions/NewSecuritiesIssuanceType3Code",
					"type": "string"
				},
				"PostingQuantity": {
					"$ref": "#/definitions/Quantity6Choice",
					"type": "object",
					"additionalProperties": false
				},
				"SafekeepingPlace": {
					"$ref": "#/definitions/SafekeepingPlaceFormat3Choice",
					"type": "object",
					"additionalProperties": false
				},
				"FractionDisposition": {
					"$ref": "#/definitions/FractionDispositionType23Choice",
					"type": "object",
					"additionalProperties": false
				},
				"CurrencyOption": {
					"$ref": "#/definitions/ActiveCurrencyCode",
					"type": "string"
				},
				"DateDetails": {
					"$ref": "#/definitions/SecurityDate6",
					"type": "object",
					"additionalProperties": false
				},
				"RateDetails": {
					"$ref": "#/definitions/CorporateActionRate49",
					"type": "object",
					"additionalProperties": false
				},
				"PriceDetails": {
					"$ref": "#/definitions/CorporateActionPrice45",
					"type": "object",
					"additionalProperties": false
				},
				"ReceivingSettlementParties": {
					"$ref": "#/definitions/SettlementParties24",
					"type": "object",
					"additionalProperties": false
				},
				"DeliveringSettlementParties": {
					"$ref": "#/definitions/SettlementParties24",
					"type": "object",
					"additionalProperties": false
				}
			},
			"required": ["FinancialInstrumentIdentification","CreditDebitIndicator","PostingQuantity","DateDetails"],
			"type": "object"
		},
		"CreditDebitCode": {
			"enum":["DBIT","CRDT"],			
			"type": "string"
		},
		"TemporaryFinancialInstrumentIndicator1Choice": {
			"oneOf":[
				{"required":["TemporaryIndicator"]},
				{"required":["Proprietary"]}
			],
			"properties":{
				"TemporaryIndicator": {
					"$ref": "#/definitions/YesNoIndicator",
					"type": "string"
				},
				"Proprietary": {
					"$ref": "#/definitions/GenericIdentification20",
					"type": "object",
					"additionalProperties": false
				}},
			"additionalProperties": false,
			"type": "object"
		},
		"YesNoIndicator" : {
		
				
			"type":"boolean"
		},
		"NewSecuritiesIssuanceType3Code": {
			"enum":["DEFE","NDEF"],			
			"type": "string"
		},
		"Quantity6Choice": {
			"oneOf":[
				{"required":["Quantity"]},
				{"required":["OriginalAndCurrentFace"]}
			],
			"properties":{
				"Quantity": {
					"$ref": "#/definitions/FinancialInstrumentQuantity1Choice",
					"type": "object",
					"additionalProperties": false
				},
				"OriginalAndCurrentFace": {
					"$ref": "#/definitions/OriginalAndCurrentQuantities1",
					"type": "object",
					"additionalProperties": false
				}},
			"additionalProperties": false,
			"type": "object"
		},
		"OriginalAndCurrentQuantities1": {
			"additionalProperties": false,
			"properties": {
				"FaceAmount": {
					"$ref": "#/definitions/ImpliedCurrencyAndAmount",
					"type": "string"
				},
				"AmortisedValue": {
					"$ref": "#/definitions/ImpliedCurrencyAndAmount",
					"type": "string"
				}
			},
			"required": ["FaceAmount","AmortisedValue"],
			"type": "object"
		},
		"SafekeepingPlaceFormat3Choice": {
			"oneOf":[
				{"required":["Identification"]},
				{"required":["Country"]},
				{"required":["TypeAndIdentification"]},
				{"required":["Proprietary"]}
			],
			"properties":{
				"Identification": {
					"$ref": "#/definitions/SafekeepingPlaceTypeAndText3",
					"type": "object",
					"additionalProperties": false
				},
				"Country": {
					"$ref": "#/definitions/CountryCode",
					"type": "string"
				},
				"TypeAndIdentification": {
					"$ref": "#/definitions/SafekeepingPlaceTypeAndAnyBICIdentifier1",
					"type": "object",
					"additionalProperties": false
				},
				"Proprietary": {
					"$ref": "#/definitions/GenericIdentification21",
					"type": "object",
					"additionalProperties": false
				}},
			"additionalProperties": false,
			"type": "object"
		},
		"SafekeepingPlaceTypeAndText3": {
			"additionalProperties": false,
			"properties": {
				"SafekeepingPlaceType": {
					"$ref": "#/definitions/SafekeepingPlace3Code",
					"type": "string"
				},
				"Identification": {
					"$ref": "#/definitions/Max35Text",
					"type": "string"
				}
			},
			"required": ["SafekeepingPlaceType"],
			"type": "object"
		},
		"SafekeepingPlace3Code": {
			"enum":["SHHE"],			
			"type": "string"
		},
		"SecurityDate6": {
			"additionalProperties": false,
			"properties": {
				"PostingDate": {
					"$ref": "#/definitions/DateAndDateTimeChoice",
					"type": "object",
					"additionalProperties": false
				},
				"AvailableDate": {
					"$ref": "#/definitions/DateFormat19Choice",
					"type": "object",
					"additionalProperties": false
				},
				"PariPassuDate": {
					"$ref": "#/definitions/DateFormat19Choice",
					"type": "object",
					"additionalProperties": false
				},
				"DividendRankingDate": {
					"$ref": "#/definitions/DateFormat19Choice",
					"type": "object",
					"additionalProperties": false
				},
				"EarliestPaymentDate": {
					"$ref": "#/definitions/DateFormat19Choice",
					"type": "object",
					"additionalProperties": false
				},
				"PaymentDate": {
					"$ref": "#/definitions/DateFormat19Choice",
					"type": "object",
					"additionalProperties": false
				}
			},
			"required": ["PostingDate"],
			"type": "object"
		},
		"CorporateActionRate49": {
			"additionalProperties": false,
			"properties": {
				"AdditionalQuantityForSubscribedResultantSecurities": {
					"$ref": "#/definitions/RatioFormat3Choice",
					"type": "object",
					"additionalProperties": false
				},
				"AdditionalQuantityForExistingSecurities": {
					"$ref": "#/definitions/RatioFormat3Choice",
					"type": "object",
					"additionalProperties": false
				},
				"NewToOld": {
					"$ref": "#/definitions/RatioFormat15Choice",
					"type": "object",
					"additionalProperties": false
				},
				"ChargesFees": {
					"$ref": "#/definitions/RateAndAmountFormat5Choice",
					"type": "object",
					"additionalProperties": false
				},
				"FiscalStamp": {
					"$ref": "#/definitions/PercentageRate",
					"type": "string"
				},
				"ApplicableRate": {
					"$ref": "#/definitions/PercentageRate",
					"type": "string"
				},
				"TaxCreditRate": {
					"items": {
						"$ref": "#/definitions/TaxCreditRateFormat2Choice"
					},
					"type": "array"
				},
				"FinancialTransactionTaxRate": {
					"$ref": "#/definitions/PercentageRate",
					"type": "string"
				}
			},
			"type": "object"
		},
		"RatioFormat3Choice": {
			"oneOf":[
				{"required":["QuantityToQuantity"]},
				{"required":["AmountToAmount"]}
			],
			"properties":{
				"QuantityToQuantity": {
					"$ref": "#/definitions/QuantityToQuantityRatio1",
					"type": "object",
					"additionalProperties": false
				},
				"AmountToAmount": {
					"$ref": "#/definitions/AmountToAmountRatio2",
					"type": "object",
					"additionalProperties": false
				}},
			"additionalProperties": false,
			"type": "object"
		},
		"QuantityToQuantityRatio1": {
			"additionalProperties": false,
			"properties": {
				"Quantity1": {
					"$ref": "#/definitions/DecimalNumber",
					"type": "string"
				},
				"Quantity2": {
					"$ref": "#/definitions/DecimalNumber",
					"type": "string"
				}
			},
			"required": ["Quantity1","Quantity2"],
			"type": "object"
		},
		"AmountToAmountRatio2": {
			"additionalProperties": false,
			"properties": {
				"Amount1": {
					"$ref": "#/definitions/ActiveCurrencyAnd13DecimalAmount",
					"type": "string"
				},
				"Amount2": {
					"$ref": "#/definitions/ActiveCurrencyAnd13DecimalAmount",
					"type": "string"
				}
			},
			"required": ["Amount1","Amount2"],
			"type": "object"
		},
		"RatioFormat15Choice": {
			"oneOf":[
				{"required":["QuantityToQuantity"]},
				{"required":["AmountToAmount"]},
				{"required":["QuantityToAmount"]}
			],
			"properties":{
				"QuantityToQuantity": {
					"$ref": "#/definitions/QuantityToQuantityRatio1",
					"type": "object",
					"additionalProperties": false
				},
				"AmountToAmount": {
					"$ref": "#/definitions/AmountToAmountRatio2",
					"type": "object",
					"additionalProperties": false
				},
				"QuantityToAmount": {
					"$ref": "#/definitions/AmountAndQuantityRatio2",
					"type": "object",
					"additionalProperties": false
				}},
			"additionalProperties": false,
			"type": "object"
		},
		"AmountAndQuantityRatio2": {
			"additionalProperties": false,
			"properties": {
				"Amount": {
					"$ref": "#/definitions/ActiveCurrencyAnd13DecimalAmount",
					"type": "string"
				},
				"Quantity": {
					"$ref": "#/definitions/DecimalNumber",
					"type": "string"
				}
			},
			"required": ["Amount","Quantity"],
			"type": "object"
		},
		"TaxCreditRateFormat2Choice": {
			"oneOf":[
				{"required":["Rate"]},
				{"required":["Amount"]},
				{"required":["RateTypeAndAmountAndRateStatus"]}
			],
			"properties":{
				"Rate": {
					"$ref": "#/definitions/PercentageRate",
					"type": "string"
				},
				"Amount": {
					"$ref": "#/definitions/ActiveCurrencyAnd13DecimalAmount",
					"type": "string"
				},
				"RateTypeAndAmountAndRateStatus": {
					"$ref": "#/definitions/RateTypeAndAmountAndStatus5",
					"type": "object",
					"additionalProperties": false
				}},
			"additionalProperties": false,
			"type": "object"
		},
		"RateTypeAndAmountAndStatus5": {
			"additionalProperties": false,
			"properties": {
				"RateType": {
					"$ref": "#/definitions/RateType10Choice",
					"type": "object",
					"additionalProperties": false
				},
				"Amount": {
					"$ref": "#/definitions/ActiveCurrencyAnd13DecimalAmount",
					"type": "string"
				},
				"RateStatus": {
					"$ref": "#/definitions/RateStatus1Choice",
					"type": "object",
					"additionalProperties": false
				}
			},
			"required": ["RateType","Amount"],
			"type": "object"
		},
		"RateType10Choice": {
			"oneOf":[
				{"required":["Code"]},
				{"required":["Proprietary"]}
			],
			"properties":{
				"Code": {
					"$ref": "#/definitions/RateType3Code",
					"type": "string"
				},
				"Proprietary": {
					"$ref": "#/definitions/GenericIdentification20",
					"type": "object",
					"additionalProperties": false
				}},
			"additionalProperties": false,
			"type": "object"
		},
		"RateType3Code": {
			"enum":["IMPU","PREC","TIER"],			
			"type": "string"
		},
		"CorporateActionPrice45": {
			"additionalProperties": false,
			"properties": {
				"CashInLieuOfSharePrice": {
					"$ref": "#/definitions/PriceFormat5Choice",
					"type": "object",
					"additionalProperties": false
				},
				"IndicativeOrMarketPrice": {
					"$ref": "#/definitions/IndicativeOrMarketPrice2Choice",
					"type": "object",
					"additionalProperties": false
				},
				"CashValueForTax": {
					"$ref": "#/definitions/AmountPrice2",
					"type": "object",
					"additionalProperties": false
				},
				"GenericCashPricePaidPerProduct": {
					"$ref": "#/definitions/PriceFormat6Choice",
					"type": "object",
					"additionalProperties": false
				},
				"GenericCashPriceReceivedPerProduct": {
					"$ref": "#/definitions/PriceFormat34Choice",
					"type": "object",
					"additionalProperties": false
				}
			},
			"type": "object"
		},
		"IndicativeOrMarketPrice2Choice": {
			"oneOf":[
				{"required":["IndicativePrice"]},
				{"required":["MarketPrice"]}
			],
			"properties":{
				"IndicativePrice": {
					"$ref": "#/definitions/PriceFormat5Choice",
					"type": "object",
					"additionalProperties": false
				},
				"MarketPrice": {
					"$ref": "#/definitions/PriceFormat5Choice",
					"type": "object",
					"additionalProperties": false
				}},
			"additionalProperties": false,
			"type": "object"
		},
		"AmountPrice2": {
			"additionalProperties": false,
			"properties": {
				"AmountPriceType": {
					"$ref": "#/definitions/AmountPriceType2Code",
					"type": "string"
				},
				"PriceValue": {
					"$ref": "#/definitions/ActiveCurrencyAnd13DecimalAmount",
					"type": "string"
				}
			},
			"required": ["AmountPriceType","PriceValue"],
			"type": "object"
		},
		"AmountPriceType2Code": {
			"enum":["ACTU"],			
			"type": "string"
		},
		"PriceFormat6Choice": {
			"oneOf":[
				{"required":["PercentagePrice"]},
				{"required":["AmountPrice"]},
				{"required":["IndexPoints"]}
			],
			"properties":{
				"PercentagePrice": {
					"$ref": "#/definitions/PercentagePrice1",
					"type": "object",
					"additionalProperties": false
				},
				"AmountPrice": {
					"$ref": "#/definitions/AmountPrice3",
					"type": "object",
					"additionalProperties": false
				},
				"IndexPoints": {
					"$ref": "#/definitions/DecimalNumber",
					"type": "string"
				}},
			"additionalProperties": false,
			"type": "object"
		},
		"PriceFormat34Choice": {
			"oneOf":[
				{"required":["PercentagePrice"]},
				{"required":["AmountPrice"]},
				{"required":["AmountPricePerFinancialInstrumentQuantity"]},
				{"required":["AmountPricePerAmount"]},
				{"required":["IndexPoints"]}
			],
			"properties":{
				"PercentagePrice": {
					"$ref": "#/definitions/PercentagePrice1",
					"type": "object",
					"additionalProperties": false
				},
				"AmountPrice": {
					"$ref": "#/definitions/AmountPrice3",
					"type": "object",
					"additionalProperties": false
				},
				"AmountPricePerFinancialInstrumentQuantity": {
					"$ref": "#/definitions/AmountPricePerFinancialInstrumentQuantity3",
					"type": "object",
					"additionalProperties": false
				},
				"AmountPricePerAmount": {
					"$ref": "#/definitions/AmountPricePerAmount2",
					"type": "object",
					"additionalProperties": false
				},
				"IndexPoints": {
					"$ref": "#/definitions/DecimalNumber",
					"type": "string"
				}},
			"additionalProperties": false,
			"type": "object"
		},
		"AmountPricePerFinancialInstrumentQuantity3": {
			"additionalProperties": false,
			"properties": {
				"AmountPriceType": {
					"$ref": "#/definitions/AmountPriceType1Code",
					"type": "string"
				},
				"PriceValue": {
					"$ref": "#/definitions/ActiveCurrencyAnd13DecimalAmount",
					"type": "string"
				},
				"FinancialInstrumentQuantity": {
					"$ref": "#/definitions/FinancialInstrumentQuantity1Choice",
					"type": "object",
					"additionalProperties": false
				}
			},
			"required": ["AmountPriceType","PriceValue","FinancialInstrumentQuantity"],
			"type": "object"
		},
		"AmountPricePerAmount2": {
			"additionalProperties": false,
			"properties": {
				"AmountPriceType": {
					"$ref": "#/definitions/AmountPriceType1Code",
					"type": "string"
				},
				"PriceValue": {
					"$ref": "#/definitions/ActiveCurrencyAnd13DecimalAmount",
					"type": "string"
				},
				"Amount": {
					"$ref": "#/definitions/ActiveCurrencyAnd13DecimalAmount",
					"type": "string"
				}
			},
			"required": ["AmountPriceType","PriceValue","Amount"],
			"type": "object"
		},
		"SettlementParties24": {
			"additionalProperties": false,
			"properties": {
				"Depository": {
					"$ref": "#/definitions/PartyIdentification47",
					"type": "object",
					"additionalProperties": false
				},
				"Party1": {
					"$ref": "#/definitions/PartyIdentificationAndAccount51",
					"type": "object",
					"additionalProperties": false
				},
				"Party2": {
					"$ref": "#/definitions/PartyIdentificationAndAccount51",
					"type": "object",
					"additionalProperties": false
				},
				"Party3": {
					"$ref": "#/definitions/PartyIdentificationAndAccount51",
					"type": "object",
					"additionalProperties": false
				}
			},
			"type": "object"
		},
		"PartyIdentification47": {
			"additionalProperties": false,
			"properties": {
				"Identification": {
					"$ref": "#/definitions/PartyIdentification39Choice",
					"type": "object",
					"additionalProperties": false
				},
				"ProcessingIdentification": {
					"$ref": "#/definitions/Max35Text",
					"type": "string"
				},
				"AdditionalInformation": {
					"$ref": "#/definitions/Max350Text",
					"type": "string"
				},
				"AlternateIdentification": {
					"items": {
						"$ref": "#/definitions/AlternatePartyIdentification2"
					},
					"type": "array"
				}
			},
			"required": ["Identification"],
			"type": "object"
		},
		"PartyIdentification39Choice": {
			"oneOf":[
				{"required":["AnyBIC"]},
				{"required":["NameAndAddress"]},
				{"required":["Country"]}
			],
			"properties":{
				"AnyBIC": {
					"$ref": "#/definitions/AnyBICIdentifier",
					"type": "string"
				},
				"NameAndAddress": {
					"$ref": "#/definitions/NameAndAddress5",
					"type": "object",
					"additionalProperties": false
				},
				"Country": {
					"$ref": "#/definitions/CountryCode",
					"type": "string"
				}},
			"additionalProperties": false,
			"type": "object"
		},
		"NameAndAddress5": {
			"additionalProperties": false,
			"properties": {
				"Name": {
					"$ref": "#/definitions/Max350Text",
					"type": "string"
				},
				"Address": {
					"$ref": "#/definitions/PostalAddress1",
					"type": "object",
					"additionalProperties": false
				}
			},
			"required": ["Name"],
			"type": "object"
		},
		"Max350Text": {
			"description": "Specifies a character string with a maximum length of 350 characters.",
			"minLength": 1,
			"maxLength": 350,
			"type": "string"
		},
		"PostalAddress1": {
			"additionalProperties": false,
			"properties": {
				"AddressType": {
					"$ref": "#/definitions/AddressType2Code",
					"type": "string"
				},
				"AddressLine": {
					"maxItems":5,
					"items": {
						"$ref": "#/definitions/Max70Text"
					},
					"type": "array"
				},
				"StreetName": {
					"$ref": "#/definitions/Max70Text",
					"type": "string"
				},
				"BuildingNumber": {
					"$ref": "#/definitions/Max16Text",
					"type": "string"
				},
				"PostCode": {
					"$ref": "#/definitions/Max16Text",
					"type": "string"
				},
				"TownName": {
					"$ref": "#/definitions/Max35Text",
					"type": "string"
				},
				"CountrySubDivision": {
					"$ref": "#/definitions/Max35Text",
					"type": "string"
				},
				"Country": {
					"$ref": "#/definitions/CountryCode",
					"type": "string"
				}
			},
			"required": ["Country"],
			"type": "object"
		},
		"AddressType2Code": {
			"enum":["HOME","BIZZ","ADDR","PBOX","MLTO","DLVY"],			
			"type": "string"
		},
		"Max70Text": {
			"description": "Specifies a character string with a maximum length of 70characters.",
			"minLength": 1,
			"maxLength": 70,
			"type": "string"
		},
		"AlternatePartyIdentification2": {
			"additionalProperties": false,
			"properties": {
				"IdentificationType": {
					"$ref": "#/definitions/IdentificationType4Choice",
					"type": "object",
					"additionalProperties": false
				},
				"Country": {
					"$ref": "#/definitions/CountryCode",
					"type": "string"
				},
				"AlternateIdentification": {
					"$ref": "#/definitions/Max35Text",
					"type": "string"
				}
			},
			"required": ["IdentificationType","Country","AlternateIdentification"],
			"type": "object"
		},
		"IdentificationType4Choice": {
			"oneOf":[
				{"required":["Code"]},
				{"required":["Proprietary"]}
			],
			"properties":{
				"Code": {
					"$ref": "#/definitions/TypeOfIdentification1Code",
					"type": "string"
				},
				"Proprietary": {
					"$ref": "#/definitions/GenericIdentification20",
					"type": "object",
					"additionalProperties": false
				}},
			"additionalProperties": false,
			"type": "object"
		},
		"TypeOfIdentification1Code": {
			"enum":["ARNU","CCPT","CHTY","CORP","DRLC","FIIN","TXID"],			
			"type": "string"
		},
		"PartyIdentificationAndAccount51": {
			"additionalProperties": false,
			"properties": {
				"Identification": {
					"$ref": "#/definitions/PartyIdentification40Choice",
					"type": "object",
					"additionalProperties": false
				},
				"SafekeepingAccount": {
					"$ref": "#/definitions/Max35Text",
					"type": "string"
				},
				"ProcessingIdentification": {
					"$ref": "#/definitions/Max35Text",
					"type": "string"
				},
				"AdditionalInformation": {
					"$ref": "#/definitions/Max350Text",
					"type": "string"
				},
				"AlternateIdentification": {
					"items": {
						"$ref": "#/definitions/AlternatePartyIdentification2"
					},
					"type": "array"
				}
			},
			"required": ["Identification"],
			"type": "object"
		},
		"PartyIdentification40Choice": {
			"oneOf":[
				{"required":["AnyBIC"]},
				{"required":["ProprietaryIdentification"]},
				{"required":["NameAndAddress"]}
			],
			"properties":{
				"AnyBIC": {
					"$ref": "#/definitions/AnyBICIdentifier",
					"type": "string"
				},
				"ProprietaryIdentification": {
					"$ref": "#/definitions/GenericIdentification19",
					"type": "object",
					"additionalProperties": false
				},
				"NameAndAddress": {
					"$ref": "#/definitions/NameAndAddress5",
					"type": "object",
					"additionalProperties": false
				}},
			"additionalProperties": false,
			"type": "object"
		},
		"CashOption30": {
			"additionalProperties": false,
			"properties": {
				"CreditDebitIndicator": {
					"$ref": "#/definitions/CreditDebitCode",
					"type": "string"
				},
				"ContractualPaymentIndicator": {
					"$ref": "#/definitions/Payment1Code",
					"type": "string"
				},
				"IncomeType": {
					"$ref": "#/definitions/GenericIdentification20",
					"type": "object",
					"additionalProperties": false
				},
				"ExemptionType": {
					"items": {
						"$ref": "#/definitions/GenericIdentification20"
					},
					"type": "array"
				},
				"Account": {
					"$ref": "#/definitions/Account8Choice",
					"type": "object",
					"additionalProperties": false
				},
				"CashParties": {
					"$ref": "#/definitions/CashParties10",
					"type": "object",
					"additionalProperties": false
				},
				"AmountDetails": {
					"$ref": "#/definitions/CorporateActionAmounts29",
					"type": "object",
					"additionalProperties": false
				},
				"DateDetails": {
					"$ref": "#/definitions/CorporateActionDate24",
					"type": "object",
					"additionalProperties": false
				},
				"ForeignExchangeDetails": {
					"$ref": "#/definitions/ForeignExchangeTerms11",
					"type": "object",
					"additionalProperties": false
				},
				"TaxVoucherDetails": {
					"$ref": "#/definitions/TaxVoucher2",
					"type": "object",
					"additionalProperties": false
				},
				"RateAndAmountDetails": {
					"$ref": "#/definitions/RateDetails15",
					"type": "object",
					"additionalProperties": false
				},
				"PriceDetails": {
					"$ref": "#/definitions/PriceDetails14",
					"type": "object",
					"additionalProperties": false
				}
			},
			"required": ["CreditDebitIndicator","AmountDetails","DateDetails"],
			"type": "object"
		},
		"Payment1Code": {
			"enum":["ACTU","CONT"],			
			"type": "string"
		},
		"Account8Choice": {
			"oneOf":[
				{"required":["CashAccount"]},
				{"required":["ChargesAccount"]},
				{"required":["TaxAccount"]}
			],
			"properties":{
				"CashAccount": {
					"$ref": "#/definitions/CashAccountIdentification5Choice",
					"type": "object",
					"additionalProperties": false
				},
				"ChargesAccount": {
					"$ref": "#/definitions/CashAccountIdentification5Choice",
					"type": "object",
					"additionalProperties": false
				},
				"TaxAccount": {
					"$ref": "#/definitions/CashAccountIdentification5Choice",
					"type": "object",
					"additionalProperties": false
				}},
			"additionalProperties": false,
			"type": "object"
		},
		"CashAccountIdentification5Choice": {
			"oneOf":[
				{"required":["IBAN"]},
				{"required":["Proprietary"]}
			],
			"properties":{
				"IBAN": {
					"$ref": "#/definitions/IBAN2007Identifier",
					"type": "string"
				},
				"Proprietary": {
					"$ref": "#/definitions/Max34Text",
					"type": "string"
				}},
			"additionalProperties": false,
			"type": "object"
		},
		"IBAN2007Identifier" : {
		
			"pattern":"^[A-Z]{2,2}[0-9]{2,2}[a-zA-Z0-9]{1,30}$",
			"type":"string"
		},
		"Max34Text": {
			"description": "Specifies a character string with a maximum length of 34 characters.",
			"minLength": 1,
			"maxLength": 34,
			"type": "string"
		},
		"CashParties10": {
			"additionalProperties": false,
			"properties": {
				"Creditor": {
					"$ref": "#/definitions/PartyIdentificationAndAccount52",
					"type": "object",
					"additionalProperties": false
				},
				"CreditorAgent": {
					"$ref": "#/definitions/PartyIdentificationAndAccount54",
					"type": "object",
					"additionalProperties": false
				},
				"MarketClaimCounterparty": {
					"$ref": "#/definitions/PartyIdentificationAndAccount52",
					"type": "object",
					"additionalProperties": false
				}
			},
			"type": "object"
		},
		"PartyIdentificationAndAccount52": {
			"additionalProperties": false,
			"properties": {
				"Identification": {
					"$ref": "#/definitions/PartyIdentification40Choice",
					"type": "object",
					"additionalProperties": false
				},
				"CashAccount": {
					"$ref": "#/definitions/CashAccountIdentification5Choice",
					"type": "object",
					"additionalProperties": false
				},
				"ProcessingIdentification": {
					"$ref": "#/definitions/Max35Text",
					"type": "string"
				},
				"AdditionalInformation": {
					"$ref": "#/definitions/Max350Text",
					"type": "string"
				},
				"AlternateIdentification": {
					"$ref": "#/definitions/AlternatePartyIdentification2",
					"type": "object",
					"additionalProperties": false
				}
			},
			"required": ["Identification"],
			"type": "object"
		},
		"PartyIdentificationAndAccount54": {
			"additionalProperties": false,
			"properties": {
				"Identification": {
					"$ref": "#/definitions/PartyIdentification42Choice",
					"type": "object",
					"additionalProperties": false
				},
				"CashAccount": {
					"$ref": "#/definitions/CashAccountIdentification5Choice",
					"type": "object",
					"additionalProperties": false
				},
				"ProcessingIdentification": {
					"$ref": "#/definitions/Max35Text",
					"type": "string"
				},
				"AdditionalInformation": {
					"$ref": "#/definitions/Max350Text",
					"type": "string"
				},
				"AlternateIdentification": {
					"$ref": "#/definitions/AlternatePartyIdentification2",
					"type": "object",
					"additionalProperties": false
				}
			},
			"required": ["Identification"],
			"type": "object"
		},
		"PartyIdentification42Choice": {
			"oneOf":[
				{"required":["BICFI"]},
				{"required":["NameAndAddress"]},
				{"required":["ProprietaryIdentification"]}
			],
			"properties":{
				"BICFI": {
					"$ref": "#/definitions/BICFIIdentifier",
					"type": "string"
				},
				"NameAndAddress": {
					"$ref": "#/definitions/NameAndAddress5",
					"type": "object",
					"additionalProperties": false
				},
				"ProprietaryIdentification": {
					"$ref": "#/definitions/GenericIdentification19",
					"type": "object",
					"additionalProperties": false
				}},
			"additionalProperties": false,
			"type": "object"
		},
		"BICFIIdentifier" : {
		
			"pattern":"^[A-Z]{6,6}[A-Z2-9][A-NP-Z0-9]([A-Z0-9]{3,3}){0,1}$",
			"type":"string"
		},
		"CorporateActionAmounts29": {
			"additionalProperties": false,
			"properties": {
				"PostingAmount": {
					"$ref": "#/definitions/ActiveCurrencyAndAmount",
					"type": "string"
				},
				"GrossCashAmount": {
					"$ref": "#/definitions/ActiveCurrencyAndAmount",
					"type": "string"
				},
				"NetCashAmount": {
					"$ref": "#/definitions/ActiveCurrencyAndAmount",
					"type": "string"
				},
				"SolicitationFees": {
					"$ref": "#/definitions/ActiveCurrencyAndAmount",
					"type": "string"
				},
				"CashInLieuOfShare": {
					"$ref": "#/definitions/ActiveCurrencyAndAmount",
					"type": "string"
				},
				"CapitalGain": {
					"$ref": "#/definitions/ActiveCurrencyAndAmount",
					"type": "string"
				},
				"InterestAmount": {
					"$ref": "#/definitions/ActiveCurrencyAndAmount",
					"type": "string"
				},
				"MarketClaimAmount": {
					"$ref": "#/definitions/ActiveCurrencyAndAmount",
					"type": "string"
				},
				"IndemnityAmount": {
					"$ref": "#/definitions/ActiveCurrencyAndAmount",
					"type": "string"
				},
				"ManufacturedDividendPaymentAmount": {
					"$ref": "#/definitions/ActiveCurrencyAndAmount",
					"type": "string"
				},
				"ReinvestmentAmount": {
					"$ref": "#/definitions/ActiveCurrencyAndAmount",
					"type": "string"
				},
				"FullyFrankedAmount": {
					"$ref": "#/definitions/ActiveCurrencyAndAmount",
					"type": "string"
				},
				"UnfrankedAmount": {
					"$ref": "#/definitions/ActiveCurrencyAndAmount",
					"type": "string"
				},
				"SundryOrOtherAmount": {
					"$ref": "#/definitions/ActiveCurrencyAndAmount",
					"type": "string"
				},
				"TaxFreeAmount": {
					"$ref": "#/definitions/ActiveCurrencyAndAmount",
					"type": "string"
				},
				"TaxDeferredAmount": {
					"$ref": "#/definitions/ActiveCurrencyAndAmount",
					"type": "string"
				},
				"ValueAddedTaxAmount": {
					"$ref": "#/definitions/ActiveCurrencyAndAmount",
					"type": "string"
				},
				"StampDutyAmount": {
					"$ref": "#/definitions/ActiveCurrencyAndAmount",
					"type": "string"
				},
				"TaxReclaimAmount": {
					"$ref": "#/definitions/ActiveCurrencyAndAmount",
					"type": "string"
				},
				"TaxCreditAmount": {
					"$ref": "#/definitions/ActiveCurrencyAndAmount",
					"type": "string"
				},
				"WithholdingOfForeignTaxAmount": {
					"$ref": "#/definitions/ActiveCurrencyAndAmount",
					"type": "string"
				},
				"WithholdingOfLocalTaxAmount": {
					"$ref": "#/definitions/ActiveCurrencyAndAmount",
					"type": "string"
				},
				"AdditionalTaxAmount": {
					"$ref": "#/definitions/ActiveCurrencyAndAmount",
					"type": "string"
				},
				"WithholdingTaxAmount": {
					"$ref": "#/definitions/ActiveCurrencyAndAmount",
					"type": "string"
				},
				"FiscalStampAmount": {
					"$ref": "#/definitions/ActiveCurrencyAndAmount",
					"type": "string"
				},
				"ExecutingBrokerAmount": {
					"$ref": "#/definitions/ActiveCurrencyAndAmount",
					"type": "string"
				},
				"PayingAgentCommissionAmount": {
					"$ref": "#/definitions/ActiveCurrencyAndAmount",
					"type": "string"
				},
				"LocalBrokerCommissionAmount": {
					"$ref": "#/definitions/ActiveCurrencyAndAmount",
					"type": "string"
				},
				"RegulatoryFeesAmount": {
					"$ref": "#/definitions/ActiveCurrencyAndAmount",
					"type": "string"
				},
				"ShippingFeesAmount": {
					"$ref": "#/definitions/ActiveCurrencyAndAmount",
					"type": "string"
				},
				"ChargesAmount": {
					"$ref": "#/definitions/ActiveCurrencyAndAmount",
					"type": "string"
				},
				"CashAmountBroughtForward": {
					"$ref": "#/definitions/ActiveCurrencyAndAmount",
					"type": "string"
				},
				"CashAmountCarriedForward": {
					"$ref": "#/definitions/ActiveCurrencyAndAmount",
					"type": "string"
				},
				"NotionalDividendPayableAmount": {
					"$ref": "#/definitions/ActiveCurrencyAndAmount",
					"type": "string"
				},
				"NotionalTaxAmount": {
					"$ref": "#/definitions/ActiveCurrencyAndAmount",
					"type": "string"
				},
				"TaxArrearsAmount": {
					"$ref": "#/definitions/ActiveCurrencyAndAmount",
					"type": "string"
				},
				"OriginalAmount": {
					"$ref": "#/definitions/ActiveCurrencyAndAmount",
					"type": "string"
				},
				"PrincipalOrCorpus": {
					"$ref": "#/definitions/ActiveCurrencyAndAmount",
					"type": "string"
				},
				"RedemptionPremiumAmount": {
					"$ref": "#/definitions/ActiveCurrencyAndAmount",
					"type": "string"
				},
				"IncomePortion": {
					"$ref": "#/definitions/ActiveCurrencyAndAmount",
					"type": "string"
				},
				"StockExchangeTax": {
					"$ref": "#/definitions/ActiveCurrencyAndAmount",
					"type": "string"
				},
				"EUTaxRetentionAmount": {
					"$ref": "#/definitions/ActiveCurrencyAndAmount",
					"type": "string"
				},
				"AccruedInterestAmount": {
					"$ref": "#/definitions/ActiveCurrencyAndAmount",
					"type": "string"
				},
				"EqualisationAmount": {
					"$ref": "#/definitions/ActiveCurrencyAndAmount",
					"type": "string"
				},
				"FATCATaxAmount": {
					"$ref": "#/definitions/ActiveCurrencyAndAmount",
					"type": "string"
				},
				"NRATaxAmount": {
					"$ref": "#/definitions/ActiveCurrencyAndAmount",
					"type": "string"
				},
				"BackUpWithholdingTaxAmount": {
					"$ref": "#/definitions/ActiveCurrencyAndAmount",
					"type": "string"
				},
				"TaxOnIncomeAmount": {
					"$ref": "#/definitions/ActiveCurrencyAndAmount",
					"type": "string"
				},
				"TransactionTax": {
					"$ref": "#/definitions/ActiveCurrencyAndAmount",
					"type": "string"
				}
			},
			"required": ["PostingAmount"],
			"type": "object"
		},
		"ActiveCurrencyAndAmount" : {
			"type":"object",
			"properties":{
				"$": {
					"maxLength":18,
					"type":"string" 
				},
				"ActiveCurrencyCode":{
					"$ref":"#/definitions/ActiveCurrencyCode"
				}
			}
			
		},
		"CorporateActionDate24": {
			"additionalProperties": false,
			"properties": {
				"PostingDate": {
					"$ref": "#/definitions/DateAndDateTimeChoice",
					"type": "object",
					"additionalProperties": false
				},
				"ValueDate": {
					"$ref": "#/definitions/DateAndDateTimeChoice",
					"type": "object",
					"additionalProperties": false
				},
				"ForeignExchangeRateFixingDate": {
					"$ref": "#/definitions/DateAndDateTimeChoice",
					"type": "object",
					"additionalProperties": false
				},
				"EarliestPaymentDate": {
					"$ref": "#/definitions/DateAndDateTimeChoice",
					"type": "object",
					"additionalProperties": false
				},
				"PaymentDate": {
					"$ref": "#/definitions/DateAndDateTimeChoice",
					"type": "object",
					"additionalProperties": false
				}
			},
			"required": ["PostingDate"],
			"type": "object"
		},
		"ForeignExchangeTerms11": {
			"additionalProperties": false,
			"properties": {
				"UnitCurrency": {
					"$ref": "#/definitions/ActiveCurrencyCode",
					"type": "string"
				},
				"QuotedCurrency": {
					"$ref": "#/definitions/ActiveCurrencyCode",
					"type": "string"
				},
				"ExchangeRate": {
					"$ref": "#/definitions/BaseOneRate",
					"type": "string"
				},
				"ResultingAmount": {
					"$ref": "#/definitions/ActiveCurrencyAndAmount",
					"type": "string"
				}
			},
			"required": ["UnitCurrency","QuotedCurrency","ExchangeRate","ResultingAmount"],
			"type": "object"
		},
		"BaseOneRate" : {
		
			"maxLength":11,
			"type":"string"
		},
		"TaxVoucher2": {
			"additionalProperties": false,
			"properties": {
				"Identification": {
					"$ref": "#/definitions/Max35Text",
					"type": "string"
				},
				"BargainDate": {
					"$ref": "#/definitions/DateAndDateTimeChoice",
					"type": "object",
					"additionalProperties": false
				},
				"BargainSettlementDate": {
					"$ref": "#/definitions/DateAndDateTimeChoice",
					"type": "object",
					"additionalProperties": false
				}
			},
			"required": ["Identification"],
			"type": "object"
		},
		"RateDetails15": {
			"additionalProperties": false,
			"properties": {
				"AdditionalTax": {
					"$ref": "#/definitions/RateAndAmountFormat5Choice",
					"type": "object",
					"additionalProperties": false
				},
				"ChargesFees": {
					"$ref": "#/definitions/RateAndAmountFormat5Choice",
					"type": "object",
					"additionalProperties": false
				},
				"FinalDividendRate": {
					"$ref": "#/definitions/ActiveCurrencyAnd13DecimalAmount",
					"type": "string"
				},
				"FiscalStamp": {
					"$ref": "#/definitions/PercentageRate",
					"type": "string"
				},
				"FullyFrankedRate": {
					"$ref": "#/definitions/RateAndAmountFormat5Choice",
					"type": "object",
					"additionalProperties": false
				},
				"GrossDividendRate": {
					"items": {
						"$ref": "#/definitions/GrossDividendRateFormat8Choice"
					},
					"type": "array"
				},
				"EarlySolicitationFeeRate": {
					"$ref": "#/definitions/RateAndAmountFormat5Choice",
					"type": "object",
					"additionalProperties": false
				},
				"ThirdPartyIncentiveRate": {
					"$ref": "#/definitions/RateAndAmountFormat5Choice",
					"type": "object",
					"additionalProperties": false
				},
				"InterestRateUsedForPayment": {
					"items": {
						"$ref": "#/definitions/InterestRateUsedForPaymentFormat2Choice"
					},
					"type": "array"
				},
				"NetDividendRate": {
					"items": {
						"$ref": "#/definitions/NetDividendRateFormat10Choice"
					},
					"type": "array"
				},
				"NonResidentRate": {
					"$ref": "#/definitions/RateAndAmountFormat5Choice",
					"type": "object",
					"additionalProperties": false
				},
				"ProvisionalDividendRate": {
					"$ref": "#/definitions/ActiveCurrencyAnd13DecimalAmount",
					"type": "string"
				},
				"ApplicableRate": {
					"$ref": "#/definitions/PercentageRate",
					"type": "string"
				},
				"SolicitationFeeRate": {
					"$ref": "#/definitions/RateAndAmountFormat5Choice",
					"type": "object",
					"additionalProperties": false
				},
				"TaxCreditRate": {
					"items": {
						"$ref": "#/definitions/TaxCreditRateFormat2Choice"
					},
					"type": "array"
				},
				"TaxRelatedRate": {
					"items": {
						"$ref": "#/definitions/RateTypeAndAmountAndStatus6"
					},
					"type": "array"
				},
				"WithholdingTaxRate": {
					"items": {
						"$ref": "#/definitions/RateFormat11Choice"
					},
					"type": "array"
				},
				"TaxOnIncome": {
					"$ref": "#/definitions/RateAndAmountFormat5Choice",
					"type": "object",
					"additionalProperties": false
				},
				"TaxOnProfits": {
					"$ref": "#/definitions/PercentageRate",
					"type": "string"
				},
				"TaxReclaimRate": {
					"$ref": "#/definitions/PercentageRate",
					"type": "string"
				},
				"WithholdingOfForeignTax": {
					"items": {
						"$ref": "#/definitions/RateAndAmountFormat21Choice"
					},
					"type": "array"
				},
				"WithholdingOfLocalTax": {
					"items": {
						"$ref": "#/definitions/RateAndAmountFormat21Choice"
					},
					"type": "array"
				},
				"EqualisationRate": {
					"$ref": "#/definitions/ActiveCurrencyAnd13DecimalAmount",
					"type": "string"
				}
			},
			"type": "object"
		},
		"GrossDividendRateFormat8Choice": {
			"oneOf":[
				{"required":["Amount"]},
				{"required":["RateTypeAndAmountAndRateStatus"]}
			],
			"properties":{
				"Amount": {
					"$ref": "#/definitions/ActiveCurrencyAnd13DecimalAmount",
					"type": "string"
				},
				"RateTypeAndAmountAndRateStatus": {
					"$ref": "#/definitions/RateTypeAndAmountAndStatus13",
					"type": "object",
					"additionalProperties": false
				}},
			"additionalProperties": false,
			"type": "object"
		},
		"RateTypeAndAmountAndStatus13": {
			"additionalProperties": false,
			"properties": {
				"RateType": {
					"$ref": "#/definitions/RateType20Choice",
					"type": "object",
					"additionalProperties": false
				},
				"Amount": {
					"$ref": "#/definitions/ActiveCurrencyAnd13DecimalAmount",
					"type": "string"
				},
				"RateStatus": {
					"$ref": "#/definitions/RateStatus1Choice",
					"type": "object",
					"additionalProperties": false
				}
			},
			"required": ["RateType","Amount"],
			"type": "object"
		},
		"RateType20Choice": {
			"oneOf":[
				{"required":["Code"]},
				{"required":["Proprietary"]}
			],
			"properties":{
				"Code": {
					"$ref": "#/definitions/GrossDividendRateType2Code",
					"type": "string"
				},
				"Proprietary": {
					"$ref": "#/definitions/GenericIdentification20",
					"type": "object",
					"additionalProperties": false
				}},
			"additionalProperties": false,
			"type": "object"
		},
		"GrossDividendRateType2Code": {
			"enum":["CAPO","FLFR","INCO","INTR","SOIC","TXBL","TXDF","TXFR","UNFR","LTCG","STCG","FUPU","PAPU","REES"],			
			"type": "string"
		},
		"NetDividendRateFormat10Choice": {
			"oneOf":[
				{"required":["Amount"]},
				{"required":["RateTypeAndAmountAndRateStatus"]}
			],
			"properties":{
				"Amount": {
					"$ref": "#/definitions/ActiveCurrencyAnd13DecimalAmount",
					"type": "string"
				},
				"RateTypeAndAmountAndRateStatus": {
					"$ref": "#/definitions/RateTypeAndAmountAndStatus14",
					"type": "object",
					"additionalProperties": false
				}},
			"additionalProperties": false,
			"type": "object"
		},
		"RateTypeAndAmountAndStatus14": {
			"additionalProperties": false,
			"properties": {
				"RateType": {
					"$ref": "#/definitions/RateType21Choice",
					"type": "object",
					"additionalProperties": false
				},
				"Amount": {
					"$ref": "#/definitions/ActiveCurrencyAnd13DecimalAmount",
					"type": "string"
				},
				"RateStatus": {
					"$ref": "#/definitions/RateStatus1Choice",
					"type": "object",
					"additionalProperties": false
				}
			},
			"required": ["RateType","Amount"],
			"type": "object"
		},
		"RateType21Choice": {
			"oneOf":[
				{"required":["Code"]},
				{"required":["Proprietary"]}
			],
			"properties":{
				"Code": {
					"$ref": "#/definitions/NetDividendRateType2Code",
					"type": "string"
				},
				"Proprietary": {
					"$ref": "#/definitions/GenericIdentification20",
					"type": "object",
					"additionalProperties": false
				}},
			"additionalProperties": false,
			"type": "object"
		},
		"NetDividendRateType2Code": {
			"enum":["CAPO","FLFR","INCO","INTR","SOIC","TXBL","TXDF","TXFR","UNFR","FUPU","PAPU","REES"],			
			"type": "string"
		},
		"PriceDetails14": {
			"additionalProperties": false,
			"properties": {
				"GenericCashPricePaidPerProduct": {
					"$ref": "#/definitions/PriceFormat6Choice",
					"type": "object",
					"additionalProperties": false
				},
				"GenericCashPriceReceivedPerProduct": {
					"$ref": "#/definitions/PriceFormat34Choice",
					"type": "object",
					"additionalProperties": false
				}
			},
			"type": "object"
		},
		"CorporateActionNarrative4": {
			"additionalProperties": false,
			"properties": {
				"DeclarationDetails": {
					"items": {
						"$ref": "#/definitions/Max350Text"
					},
					"type": "array"
				},
				"AdditionalText": {
					"items": {
						"$ref": "#/definitions/Max350Text"
					},
					"type": "array"
				},
				"NarrativeVersion": {
					"items": {
						"$ref": "#/definitions/Max350Text"
					},
					"type": "array"
				},
				"RegistrationDetails": {
					"items": {
						"$ref": "#/definitions/Max350Text"
					},
					"type": "array"
				},
				"InformationConditions": {
					"items": {
						"$ref": "#/definitions/Max350Text"
					},
					"type": "array"
				},
				"InformationToComplyWith": {
					"items": {
						"$ref": "#/definitions/Max350Text"
					},
					"type": "array"
				},
				"PartyContactNarrative": {
					"items": {
						"$ref": "#/definitions/Max350Text"
					},
					"type": "array"
				},
				"TaxationConditions": {
					"items": {
						"$ref": "#/definitions/Max350Text"
					},
					"type": "array"
				},
				"BasketOrIndexInformation": {
					"items": {
						"$ref": "#/definitions/Max350Text"
					},
					"type": "array"
				}
			},
			"type": "object"
		},
		"PartyIdentification46Choice": {
			"oneOf":[
				{"required":["AnyBIC"]},
				{"required":["ProprietaryIdentification"]},
				{"required":["NameAndAddress"]}
			],
			"properties":{
				"AnyBIC": {
					"$ref": "#/definitions/AnyBICIdentifier",
					"type": "string"
				},
				"ProprietaryIdentification": {
					"$ref": "#/definitions/GenericIdentification19",
					"type": "object",
					"additionalProperties": false
				},
				"NameAndAddress": {
					"$ref": "#/definitions/NameAndAddress5",
					"type": "object",
					"additionalProperties": false
				}},
			"additionalProperties": false,
			"type": "object"
		},
		"SupplementaryData1": {
			"additionalProperties": false,
			"properties": {
				"PlaceAndName": {
					"$ref": "#/definitions/Max350Text",
					"type": "string"
				},
				"Envelope": {
					"$ref": "#/definitions/SupplementaryDataEnvelope1",
					"type": "object",
					"additionalProperties": false
				}
			},
			"required": ["Envelope"],
			"type": "object"
		},
		"SupplementaryDataEnvelope1" : {
		
			"type":"object"
		},
		"CorporateActionMovementConfirmationV05":{
			"additionalProperties": false,
			"properties": {
		
				"NotificationIdentification": {
					"$ref": "#/definitions/DocumentIdentification15",
					"type": "object",
					"additionalProperties": false
				},
				"MovementPreliminaryAdviceIdentification": {
					"$ref": "#/definitions/DocumentIdentification15",
					"type": "object",
					"additionalProperties": false
				},
				"InstructionIdentification": {
					"$ref": "#/definitions/DocumentIdentification9",
					"type": "object",
					"additionalProperties": false
				},
				"OtherDocumentIdentification": {
					"items": {
						"$ref": "#/definitions/DocumentIdentification13"
					},
					"type": "array"
				},
				"EventsLinkage": {
					"items": {
						"$ref": "#/definitions/CorporateActionEventReference1"
					},
					"type": "array"
				},
				"CorporateActionGeneralInformation": {
					"$ref": "#/definitions/CorporateActionGeneralInformation50",
					"type": "object",
					"additionalProperties": false
				},
				"AccountDetails": {
					"$ref": "#/definitions/AccountAndBalance26",
					"type": "object",
					"additionalProperties": false
				},
				"CorporateActionDetails": {
					"$ref": "#/definitions/CorporateAction14",
					"type": "object",
					"additionalProperties": false
				},
				"CorporateActionConfirmationDetails": {
					"$ref": "#/definitions/CorporateActionOption102",
					"type": "object",
					"additionalProperties": false
				},
				"AdditionalInformation": {
					"$ref": "#/definitions/CorporateActionNarrative4",
					"type": "object",
					"additionalProperties": false
				},
				"IssuerAgent": {
					"items": {
						"$ref": "#/definitions/PartyIdentification46Choice"
					},
					"type": "array"
				},
				"PayingAgent": {
					"items": {
						"$ref": "#/definitions/PartyIdentification46Choice"
					},
					"type": "array"
				},
				"SubPayingAgent": {
					"items": {
						"$ref": "#/definitions/PartyIdentification46Choice"
					},
					"type": "array"
				},
				"SupplementaryData": {
					"items": {
						"$ref": "#/definitions/SupplementaryData1"
					},
					"type": "array"
				}
			},
			"required": [
		"CorporateActionGeneralInformation","AccountDetails","CorporateActionConfirmationDetails"],
			"type": "object"
		}
	},
	"properties": {
	    "@xmlns": {
			"default": "urn:iso:std:iso:20022:tech:json:seev.036.001.05"
		},
		"Corporate_Action_Movement_Confirmation": {
			"$ref": "#/definitions/CorporateActionMovementConfirmationV05"
		}
	},
	"type": "object"
}
